[
    {
        "article_id": "0548603021",
        "product_code": "0548603",
        "prod_name": "Sara s/s",
        "product_type_no": "255",
        "product_type_name": "T-shirt",
        "product_group_name": "Garment Upper body",
        "graphical_appearance_no": "1010016",
        "graphical_appearance_name": "Solid",
        "colour_group_code": "19",
        "colour_group_name": "Greenish Khaki",
        "perceived_colour_value_id": "2",
        "perceived_colour_value_name": "Medium Dusty",
        "perceived_colour_master_id": "20",
        "perceived_colour_master_name": "Khaki green",
        "department_no": "2032",
        "department_name": "Jersey",
        "index_code": "A",
        "index_name": "Ladieswear",
        "index_group_no": "1",
        "index_group_name": "Ladieswear",
        "section_no": "8",
        "section_name": "Mama",
        "garment_group_no": "1005",
        "garment_group_name": "Jersey Fancy",
        "detail_desc": "Fitted top in soft cotton jersey with short sleeves and gathers in the sides for best fit."
    },
    {
        "article_id": "0548603022",
        "product_code": "0548603",
        "prod_name": "Sara s/s",
        "product_type_no": "255",
        "product_type_name": "T-shirt",
        "product_group_name": "Garment Upper body",
        "graphical_appearance_no": "1010001",
        "graphical_appearance_name": "All over pattern",
        "colour_group_code": "06",
        "colour_group_name": "Light Grey",
        "perceived_colour_value_id": "1",
        "perceived_colour_value_name": "Dusty Light",
        "perceived_colour_master_id": "12",
        "perceived_colour_master_name": "Grey",
        "department_no": "2032",
        "department_name": "Jersey",
        "index_code": "A",
        "index_name": "Ladieswear",
        "index_group_no": "1",
        "index_group_name": "Ladieswear",
        "section_no": "8",
        "section_name": "Mama",
        "garment_group_no": "1005",
        "garment_group_name": "Jersey Fancy",
        "detail_desc": "Fitted top in soft cotton jersey with short sleeves and gathers in the sides for best fit."
    },
    {
        "article_id": "0548613003",
        "product_code": "0548613",
        "prod_name": "Jordan",
        "product_type_no": "255",
        "product_type_name": "T-shirt",
        "product_group_name": "Garment Upper body",
        "graphical_appearance_no": "1010016",
        "graphical_appearance_name": "Solid",
        "colour_group_code": "32",
        "colour_group_name": "Orange",
        "perceived_colour_value_id": "5",
        "perceived_colour_value_name": "Bright",
        "perceived_colour_master_id": "3",
        "perceived_colour_master_name": "Orange",
        "department_no": "1666",
        "department_name": "Jersey",
        "index_code": "A",
        "index_name": "Ladieswear",
        "index_group_no": "1",
        "index_group_name": "Ladieswear",
        "section_no": "11",
        "section_name": "Womens Tailoring",
        "garment_group_no": "1005",
        "garment_group_name": "Jersey Fancy",
        "detail_desc": "Short-sleeved jersey top with a chest pocket and gently rounded hem. Longer at the back."
    },
    {
        "article_id": "0548613004",
        "product_code": "0548613",
        "prod_name": "Jordan (1)",
        "product_type_no": "255",
        "product_type_name": "T-shirt",
        "product_group_name": "Garment Upper body",
        "graphical_appearance_no": "1010016",
        "graphical_appearance_name": "Solid",
        "colour_group_code": "51",
        "colour_group_name": "Light Pink",
        "perceived_colour_value_id": "1",
        "perceived_colour_value_name": "Dusty Light",
        "perceived_colour_master_id": "4",
        "perceived_colour_master_name": "Pink",
        "department_no": "1666",
        "department_name": "Jersey",
        "index_code": "A",
        "index_name": "Ladieswear",
        "index_group_no": "1",
        "index_group_name": "Ladieswear",
        "section_no": "11",
        "section_name": "Womens Tailoring",
        "garment_group_no": "1005",
        "garment_group_name": "Jersey Fancy",
        "detail_desc": "Short-sleeved jersey top with a chest pocket and gently rounded hem. Longer at the back."
    },
    {
        "article_id": "0548613005",
        "product_code": "0548613",
        "prod_name": "Jordan",
        "product_type_no": "255",
        "product_type_name": "T-shirt",
        "product_group_name": "Garment Upper body",
        "graphical_appearance_no": "1010016",
        "graphical_appearance_name": "Solid",
        "colour_group_code": "10",
        "colour_group_name": "White",
        "perceived_colour_value_id": "3",
        "perceived_colour_value_name": "Light",
        "perceived_colour_master_id": "9",
        "perceived_colour_master_name": "White",
        "department_no": "1666",
        "department_name": "Jersey",
        "index_code": "A",
        "index_name": "Ladieswear",
        "index_group_no": "1",
        "index_group_name": "Ladieswear",
        "section_no": "11",
        "section_name": "Womens Tailoring",
        "garment_group_no": "1005",
        "garment_group_name": "Jersey Fancy",
        "detail_desc": "Short-sleeved jersey top with a chest pocket and gently rounded hem. Longer at the back."
    },
    {
        "article_id": "0548613026",
        "product_code": "0548613",
        "prod_name": "Jordan",
        "product_type_no": "255",
        "product_type_name": "T-shirt",
        "product_group_name": "Garment Upper body",
        "graphical_appearance_no": "1010016",
        "graphical_appearance_name": "Solid",
        "colour_group_code": "19",
        "colour_group_name": "Greenish Khaki",
        "perceived_colour_value_id": "4",
        "perceived_colour_value_name": "Dark",
        "perceived_colour_master_id": "20",
        "perceived_colour_master_name": "Khaki green",
        "department_no": "1666",
        "department_name": "Jersey",
        "index_code": "A",
        "index_name": "Ladieswear",
        "index_group_no": "1",
        "index_group_name": "Ladieswear",
        "section_no": "11",
        "section_name": "Womens Tailoring",
        "garment_group_no": "1005",
        "garment_group_name": "Jersey Fancy",
        "detail_desc": "Short-sleeved jersey top with a chest pocket and gently rounded hem. Longer at the back."
    },
    {
        "article_id": "0548613028",
        "product_code": "0548613",
        "prod_name": "Jordan",
        "product_type_no": "255",
        "product_type_name": "T-shirt",
        "product_group_name": "Garment Upper body",
        "graphical_appearance_no": "1010001",
        "graphical_appearance_name": "All over pattern",
        "colour_group_code": "73",
        "colour_group_name": "Dark Blue",
        "perceived_colour_value_id": "4",
        "perceived_colour_value_name": "Dark",
        "perceived_colour_master_id": "2",
        "perceived_colour_master_name": "Blue",
        "department_no": "1666",
        "department_name": "Jersey",
        "index_code": "A",
        "index_name": "Ladieswear",
        "index_group_no": "1",
        "index_group_name": "Ladieswear",
        "section_no": "11",
        "section_name": "Womens Tailoring",
        "garment_group_no": "1005",
        "garment_group_name": "Jersey Fancy",
        "detail_desc": "Short-sleeved jersey top with a chest pocket and gently rounded hem. Longer at the back."
    },
    {
        "article_id": "0548613029",
        "product_code": "0548613",
        "prod_name": "Jordan",
        "product_type_no": "255",
        "product_type_name": "T-shirt",
        "product_group_name": "Garment Upper body",
        "graphical_appearance_no": "1010016",
        "graphical_appearance_name": "Solid",
        "colour_group_code": "09",
        "colour_group_name": "Black",
        "perceived_colour_value_id": "4",
        "perceived_colour_value_name": "Dark",
        "perceived_colour_master_id": "5",
        "perceived_colour_master_name": "Black",
        "department_no": "1666",
        "department_name": "Jersey",
        "index_code": "A",
        "index_name": "Ladieswear",
        "index_group_no": "1",
        "index_group_name": "Ladieswear",
        "section_no": "11",
        "section_name": "Womens Tailoring",
        "garment_group_no": "1005",
        "garment_group_name": "Jersey Fancy",
        "detail_desc": "Short-sleeved jersey top with a chest pocket and gently rounded hem. Longer at the back."
    },
    {
        "article_id": "0548613030",
        "product_code": "0548613",
        "prod_name": "Jordan",
        "product_type_no": "255",
        "product_type_name": "T-shirt",
        "product_group_name": "Garment Upper body",
        "graphical_appearance_no": "1010016",
        "graphical_appearance_name": "Solid",
        "colour_group_code": "93",
        "colour_group_name": "Dark Green",
        "perceived_colour_value_id": "4",
        "perceived_colour_value_name": "Dark",
        "perceived_colour_master_id": "19",
        "perceived_colour_master_name": "Green",
        "department_no": "1666",
        "department_name": "Jersey",
        "index_code": "A",
        "index_name": "Ladieswear",
        "index_group_no": "1",
        "index_group_name": "Ladieswear",
        "section_no": "11",
        "section_name": "Womens Tailoring",
        "garment_group_no": "1005",
        "garment_group_name": "Jersey Fancy",
        "detail_desc": "Short-sleeved jersey top with a chest pocket and gently rounded hem. Longer at the back."
    },
    {
        "article_id": "0548613032",
        "product_code": "0548613",
        "prod_name": "Jordan",
        "product_type_no": "255",
        "product_type_name": "T-shirt",
        "product_group_name": "Garment Upper body",
        "graphical_appearance_no": "1010016",
        "graphical_appearance_name": "Solid",
        "colour_group_code": "51",
        "colour_group_name": "Light Pink",
        "perceived_colour_value_id": "1",
        "perceived_colour_value_name": "Dusty Light",
        "perceived_colour_master_id": "4",
        "perceived_colour_master_name": "Pink",
        "department_no": "1666",
        "department_name": "Jersey",
        "index_code": "A",
        "index_name": "Ladieswear",
        "index_group_no": "1",
        "index_group_name": "Ladieswear",
        "section_no": "11",
        "section_name": "Womens Tailoring",
        "garment_group_no": "1005",
        "garment_group_name": "Jersey Fancy",
        "detail_desc": "Short-sleeved jersey top with a chest pocket and gently rounded hem. Longer at the back."
    },
    {
        "article_id": "0548613035",
        "product_code": "0548613",
        "prod_name": "Jordan",
        "product_type_no": "255",
        "product_type_name": "T-shirt",
        "product_group_name": "Garment Upper body",
        "graphical_appearance_no": "1010016",
        "graphical_appearance_name": "Solid",
        "colour_group_code": "72",
        "colour_group_name": "Blue",
        "perceived_colour_value_id": "7",
        "perceived_colour_value_name": "Medium",
        "perceived_colour_master_id": "2",
        "perceived_colour_master_name": "Blue",
        "department_no": "1666",
        "department_name": "Jersey",
        "index_code": "A",
        "index_name": "Ladieswear",
        "index_group_no": "1",
        "index_group_name": "Ladieswear",
        "section_no": "11",
        "section_name": "Womens Tailoring",
        "garment_group_no": "1005",
        "garment_group_name": "Jersey Fancy",
        "detail_desc": "Short-sleeved jersey top with a chest pocket and gently rounded hem. Longer at the back."
    },
    {
        "article_id": "0548613036",
        "product_code": "0548613",
        "prod_name": "Jordan (1)",
        "product_type_no": "255",
        "product_type_name": "T-shirt",
        "product_group_name": "Garment Upper body",
        "graphical_appearance_no": "1010010",
        "graphical_appearance_name": "Melange",
        "colour_group_code": "07",
        "colour_group_name": "Grey",
        "perceived_colour_value_id": "1",
        "perceived_colour_value_name": "Dusty Light",
        "perceived_colour_master_id": "12",
        "perceived_colour_master_name": "Grey",
        "department_no": "1666",
        "department_name": "Jersey",
        "index_code": "A",
        "index_name": "Ladieswear",
        "index_group_no": "1",
        "index_group_name": "Ladieswear",
        "section_no": "11",
        "section_name": "Womens Tailoring",
        "garment_group_no": "1005",
        "garment_group_name": "Jersey Fancy",
        "detail_desc": "Short-sleeved jersey top with a chest pocket and gently rounded hem. Longer at the back."
    },
    {
        "article_id": "0548613038",
        "product_code": "0548613",
        "prod_name": "Jordan (1)",
        "product_type_no": "255",
        "product_type_name": "T-shirt",
        "product_group_name": "Garment Upper body",
        "graphical_appearance_no": "1010016",
        "graphical_appearance_name": "Solid",
        "colour_group_code": "19",
        "colour_group_name": "Greenish Khaki",
        "perceived_colour_value_id": "4",
        "perceived_colour_value_name": "Dark",
        "perceived_colour_master_id": "20",
        "perceived_colour_master_name": "Khaki green",
        "department_no": "1666",
        "department_name": "Jersey",
        "index_code": "A",
        "index_name": "Ladieswear",
        "index_group_no": "1",
        "index_group_name": "Ladieswear",
        "section_no": "11",
        "section_name": "Womens Tailoring",
        "garment_group_no": "1005",
        "garment_group_name": "Jersey Fancy",
        "detail_desc": "Short-sleeved jersey top with a chest pocket and gently rounded hem. Longer at the back."
    },
    {
        "article_id": "0548613040",
        "product_code": "0548613",
        "prod_name": "Jordan",
        "product_type_no": "255",
        "product_type_name": "T-shirt",
        "product_group_name": "Garment Upper body",
        "graphical_appearance_no": "1010016",
        "graphical_appearance_name": "Solid",
        "colour_group_code": "93",
        "colour_group_name": "Dark Green",
        "perceived_colour_value_id": "4",
        "perceived_colour_value_name": "Dark",
        "perceived_colour_master_id": "20",
        "perceived_colour_master_name": "Khaki green",
        "department_no": "1666",
        "department_name": "Jersey",
        "index_code": "A",
        "index_name": "Ladieswear",
        "index_group_no": "1",
        "index_group_name": "Ladieswear",
        "section_no": "11",
        "section_name": "Womens Tailoring",
        "garment_group_no": "1005",
        "garment_group_name": "Jersey Fancy",
        "detail_desc": "Short-sleeved jersey top with a chest pocket and gently rounded hem. Longer at the back."
    },
    {
        "article_id": "0548613042",
        "product_code": "0548613",
        "prod_name": "Jordan",
        "product_type_no": "255",
        "product_type_name": "T-shirt",
        "product_group_name": "Garment Upper body",
        "graphical_appearance_no": "1010016",
        "graphical_appearance_name": "Solid",
        "colour_group_code": "22",
        "colour_group_name": "Yellow",
        "perceived_colour_value_id": "1",
        "perceived_colour_value_name": "Dusty Light",
        "perceived_colour_master_id": "8",
        "perceived_colour_master_name": "Yellow",
        "department_no": "1666",
        "department_name": "Jersey",
        "index_code": "A",
        "index_name": "Ladieswear",
        "index_group_no": "1",
        "index_group_name": "Ladieswear",
        "section_no": "11",
        "section_name": "Womens Tailoring",
        "garment_group_no": "1005",
        "garment_group_name": "Jersey Fancy",
        "detail_desc": "Short-sleeved jersey top with a chest pocket and gently rounded hem. Longer at the back."
    },
    {
        "article_id": "0548614001",
        "product_code": "0548614",
        "prod_name": "SPEED Tessan",
        "product_type_no": "255",
        "product_type_name": "T-shirt",
        "product_group_name": "Garment Upper body",
        "graphical_appearance_no": "1010016",
        "graphical_appearance_name": "Solid",
        "colour_group_code": "10",
        "colour_group_name": "White",
        "perceived_colour_value_id": "3",
        "perceived_colour_value_name": "Light",
        "perceived_colour_master_id": "9",
        "perceived_colour_master_name": "White",
        "department_no": "1666",
        "department_name": "Jersey",
        "index_code": "A",
        "index_name": "Ladieswear",
        "index_group_no": "1",
        "index_group_name": "Ladieswear",
        "section_no": "11",
        "section_name": "Womens Tailoring",
        "garment_group_no": "1005",
        "garment_group_name": "Jersey Fancy",
        "detail_desc": "V-neck top in soft jersey with short sleeves with sewn-in turn-ups, and short slits in the sides."
    },
    {
        "article_id": "0548614007",
        "product_code": "0548614",
        "prod_name": "SPEED Tessan",
        "product_type_no": "255",
        "product_type_name": "T-shirt",
        "product_group_name": "Garment Upper body",
        "graphical_appearance_no": "1010016",
        "graphical_appearance_name": "Solid",
        "colour_group_code": "52",
        "colour_group_name": "Pink",
        "perceived_colour_value_id": "2",
        "perceived_colour_value_name": "Medium Dusty",
        "perceived_colour_master_id": "4",
        "perceived_colour_master_name": "Pink",
        "department_no": "1666",
        "department_name": "Jersey",
        "index_code": "A",
        "index_name": "Ladieswear",
        "index_group_no": "1",
        "index_group_name": "Ladieswear",
        "section_no": "11",
        "section_name": "Womens Tailoring",
        "garment_group_no": "1005",
        "garment_group_name": "Jersey Fancy",
        "detail_desc": "V-neck top in soft jersey with short sleeves with sewn-in turn-ups, and short slits in the sides."
    },
    {
        "article_id": "0548614012",
        "product_code": "0548614",
        "prod_name": "Tessan",
        "product_type_no": "255",
        "product_type_name": "T-shirt",
        "product_group_name": "Garment Upper body",
        "graphical_appearance_no": "1010010",
        "graphical_appearance_name": "Melange",
        "colour_group_code": "07",
        "colour_group_name": "Grey",
        "perceived_colour_value_id": "1",
        "perceived_colour_value_name": "Dusty Light",
        "perceived_colour_master_id": "12",
        "perceived_colour_master_name": "Grey",
        "department_no": "1666",
        "department_name": "Jersey",
        "index_code": "A",
        "index_name": "Ladieswear",
        "index_group_no": "1",
        "index_group_name": "Ladieswear",
        "section_no": "11",
        "section_name": "Womens Tailoring",
        "garment_group_no": "1005",
        "garment_group_name": "Jersey Fancy",
        "detail_desc": "V-neck top in soft jersey with short sleeves with sewn-in turn-ups, and short slits in the sides."
    },
    {
        "article_id": "0548614013",
        "product_code": "0548614",
        "prod_name": "Tessan",
        "product_type_no": "255",
        "product_type_name": "T-shirt",
        "product_group_name": "Garment Upper body",
        "graphical_appearance_no": "1010016",
        "graphical_appearance_name": "Solid",
        "colour_group_code": "73",
        "colour_group_name": "Dark Blue",
        "perceived_colour_value_id": "4",
        "perceived_colour_value_name": "Dark",
        "perceived_colour_master_id": "2",
        "perceived_colour_master_name": "Blue",
        "department_no": "1666",
        "department_name": "Jersey",
        "index_code": "A",
        "index_name": "Ladieswear",
        "index_group_no": "1",
        "index_group_name": "Ladieswear",
        "section_no": "11",
        "section_name": "Womens Tailoring",
        "garment_group_no": "1005",
        "garment_group_name": "Jersey Fancy",
        "detail_desc": "V-neck top in soft jersey with short sleeves with sewn-in turn-ups, and short slits in the sides."
    },
    {
        "article_id": "0548657001",
        "product_code": "0548657",
        "prod_name": "Lova catsuit",
        "product_type_no": "272",
        "product_type_name": "Trousers",
        "product_group_name": "Garment Lower body",
        "graphical_appearance_no": "1010016",
        "graphical_appearance_name": "Solid",
        "colour_group_code": "09",
        "colour_group_name": "Black",
        "perceived_colour_value_id": "4",
        "perceived_colour_value_name": "Dark",
        "perceived_colour_master_id": "5",
        "perceived_colour_master_name": "Black",
        "department_no": "1722",
        "department_name": "Trouser",
        "index_code": "A",
        "index_name": "Ladieswear",
        "index_group_no": "1",
        "index_group_name": "Ladieswear",
        "section_no": "15",
        "section_name": "Womens Everyday Collection",
        "garment_group_no": "1009",
        "garment_group_name": "Trousers",
        "detail_desc": "Fitted jumpsuit in sturdy jersey with a heart-shaped neckline at the top, wide shoulder straps and a concealed zip at the back. Slim legs with sewn-in creases."
    },
    {
        "article_id": "0548659001",
        "product_code": "0548659",
        "prod_name": "Lola trouser",
        "product_type_no": "272",
        "product_type_name": "Trousers",
        "product_group_name": "Garment Lower body",
        "graphical_appearance_no": "1010016",
        "graphical_appearance_name": "Solid",
        "colour_group_code": "09",
        "colour_group_name": "Black",
        "perceived_colour_value_id": "4",
        "perceived_colour_value_name": "Dark",
        "perceived_colour_master_id": "5",
        "perceived_colour_master_name": "Black",
        "department_no": "1722",
        "department_name": "Trouser",
        "index_code": "A",
        "index_name": "Ladieswear",
        "index_group_no": "1",
        "index_group_name": "Ladieswear",
        "section_no": "15",
        "section_name": "Womens Everyday Collection",
        "garment_group_no": "1009",
        "garment_group_name": "Trousers",
        "detail_desc": "High-waisted trousers in washed stretch twill with a concealed zip at one side and slim legs."
    },
    {
        "article_id": "0548659003",
        "product_code": "0548659",
        "prod_name": "Lola trouser",
        "product_type_no": "272",
        "product_type_name": "Trousers",
        "product_group_name": "Garment Lower body",
        "graphical_appearance_no": "1010009",
        "graphical_appearance_name": "Glittering/Metallic",
        "colour_group_code": "08",
        "colour_group_name": "Dark Grey",
        "perceived_colour_value_id": "4",
        "perceived_colour_value_name": "Dark",
        "perceived_colour_master_id": "12",
        "perceived_colour_master_name": "Grey",
        "department_no": "1722",
        "department_name": "Trouser",
        "index_code": "A",
        "index_name": "Ladieswear",
        "index_group_no": "1",
        "index_group_name": "Ladieswear",
        "section_no": "15",
        "section_name": "Womens Everyday Collection",
        "garment_group_no": "1009",
        "garment_group_name": "Trousers",
        "detail_desc": "High-waisted trousers in washed stretch twill with a concealed zip at one side and slim legs."
    },
    {
        "article_id": "0548659005",
        "product_code": "0548659",
        "prod_name": "Lola trouser",
        "product_type_no": "272",
        "product_type_name": "Trousers",
        "product_group_name": "Garment Lower body",
        "graphical_appearance_no": "1010009",
        "graphical_appearance_name": "Glittering/Metallic",
        "colour_group_code": "06",
        "colour_group_name": "Light Grey",
        "perceived_colour_value_id": "1",
        "perceived_colour_value_name": "Dusty Light",
        "perceived_colour_master_id": "12",
        "perceived_colour_master_name": "Grey",
        "department_no": "1722",
        "department_name": "Trouser",
        "index_code": "A",
        "index_name": "Ladieswear",
        "index_group_no": "1",
        "index_group_name": "Ladieswear",
        "section_no": "15",
        "section_name": "Womens Everyday Collection",
        "garment_group_no": "1009",
        "garment_group_name": "Trousers",
        "detail_desc": "High-waisted trousers in washed stretch twill with a concealed zip at one side and slim legs."
    },
    {
        "article_id": "0548659007",
        "product_code": "0548659",
        "prod_name": "Lola trouser",
        "product_type_no": "272",
        "product_type_name": "Trousers",
        "product_group_name": "Garment Lower body",
        "graphical_appearance_no": "1010017",
        "graphical_appearance_name": "Stripe",
        "colour_group_code": "12",
        "colour_group_name": "Light Beige",
        "perceived_colour_value_id": "1",
        "perceived_colour_value_name": "Dusty Light",
        "perceived_colour_master_id": "9",
        "perceived_colour_master_name": "White",
        "department_no": "1722",
        "department_name": "Trouser",
        "index_code": "A",
        "index_name": "Ladieswear",
        "index_group_no": "1",
        "index_group_name": "Ladieswear",
        "section_no": "15",
        "section_name": "Womens Everyday Collection",
        "garment_group_no": "1009",
        "garment_group_name": "Trousers",
        "detail_desc": "High-waisted trousers in washed stretch twill with a concealed zip at one side and slim legs."
    },
    {
        "article_id": "0548696001",
        "product_code": "0548696",
        "prod_name": "Freddan",
        "product_type_no": "265",
        "product_type_name": "Dress",
        "product_group_name": "Garment Full body",
        "graphical_appearance_no": "1010016",
        "graphical_appearance_name": "Solid",
        "colour_group_code": "32",
        "colour_group_name": "Orange",
        "perceived_colour_value_id": "5",
        "perceived_colour_value_name": "Bright",
        "perceived_colour_master_id": "3",
        "perceived_colour_master_name": "Orange",
        "department_no": "1322",
        "department_name": "Dress",
        "index_code": "A",
        "index_name": "Ladieswear",
        "index_group_no": "1",
        "index_group_name": "Ladieswear",
        "section_no": "15",
        "section_name": "Womens Everyday Collection",
        "garment_group_no": "1013",
        "garment_group_name": "Dresses Ladies",
        "detail_desc": "Straight-cut dress in a cr\u00eape weave with narrow adjustable shoulder straps and a concealed zip at the back. Lined at the top."
    },
    {
        "article_id": "0548724001",
        "product_code": "0548724",
        "prod_name": "Palermo poncho",
        "product_type_no": "80",
        "product_type_name": "Scarf",
        "product_group_name": "Accessories",
        "graphical_appearance_no": "1010001",
        "graphical_appearance_name": "All over pattern",
        "colour_group_code": "09",
        "colour_group_name": "Black",
        "perceived_colour_value_id": "4",
        "perceived_colour_value_name": "Dark",
        "perceived_colour_master_id": "5",
        "perceived_colour_master_name": "Black",
        "department_no": "3945",
        "department_name": "Knit & Woven",
        "index_code": "D",
        "index_name": "Divided",
        "index_group_no": "2",
        "index_group_name": "Divided",
        "section_no": "52",
        "section_name": "Divided Accessories",
        "garment_group_no": "1019",
        "garment_group_name": "Accessories",
        "detail_desc": "Poncho in a soft jacquard weave with a fringed hem."
    },
    {
        "article_id": "0548738001",
        "product_code": "0548738",
        "prod_name": "SKINNY SUNBEAM PINK",
        "product_type_no": "272",
        "product_type_name": "Trousers",
        "product_group_name": "Garment Lower body",
        "graphical_appearance_no": "1010016",
        "graphical_appearance_name": "Solid",
        "colour_group_code": "51",
        "colour_group_name": "Light Pink",
        "perceived_colour_value_id": "3",
        "perceived_colour_value_name": "Light",
        "perceived_colour_master_id": "4",
        "perceived_colour_master_name": "Pink",
        "department_no": "8917",
        "department_name": "Young Girl Denim",
        "index_code": "I",
        "index_name": "Children Sizes 134-170",
        "index_group_no": "4",
        "index_group_name": "Baby/Children",
        "section_no": "77",
        "section_name": "Young Girl",
        "garment_group_no": "1016",
        "garment_group_name": "Trousers Denim",
        "detail_desc": "Skinny-fit jeans in superstretch, flexible denim for maximum mobility with hard-worn details, an adjustable elasticated waist (in sizes 8-12Y), zip fly, fake front pockets and real back pockets."
    },
    {
        "article_id": "0548744001",
        "product_code": "0548744",
        "prod_name": "SKINNY TRASH BLING PIPER",
        "product_type_no": "272",
        "product_type_name": "Trousers",
        "product_group_name": "Garment Lower body",
        "graphical_appearance_no": "1010016",
        "graphical_appearance_name": "Solid",
        "colour_group_code": "72",
        "colour_group_name": "Blue",
        "perceived_colour_value_id": "2",
        "perceived_colour_value_name": "Medium Dusty",
        "perceived_colour_master_id": "2",
        "perceived_colour_master_name": "Blue",
        "department_no": "8917",
        "department_name": "Young Girl Denim",
        "index_code": "I",
        "index_name": "Children Sizes 134-170",
        "index_group_no": "4",
        "index_group_name": "Baby/Children",
        "section_no": "77",
        "section_name": "Young Girl",
        "garment_group_no": "1016",
        "garment_group_name": "Trousers Denim",
        "detail_desc": "Skinny-fit jeans in washed superstretch denim with hard-worn and sequined details, an adjustable elasticated waist (in sizes 8-12Y) and zip fly. Fake front pockets,real back pocket and cut-off, raw-edge hems."
    },
    {
        "article_id": "0548757002",
        "product_code": "0548757",
        "prod_name": "ANGELICA Strawhat",
        "product_type_no": "76",
        "product_type_name": "Hat/brim",
        "product_group_name": "Accessories",
        "graphical_appearance_no": "1010016",
        "graphical_appearance_name": "Solid",
        "colour_group_code": "12",
        "colour_group_name": "Light Beige",
        "perceived_colour_value_id": "1",
        "perceived_colour_value_name": "Dusty Light",
        "perceived_colour_master_id": "11",
        "perceived_colour_master_name": "Beige",
        "department_no": "4322",
        "department_name": "Young Girl Big Acc",
        "index_code": "J",
        "index_name": "Children Accessories, Swimwear",
        "index_group_no": "4",
        "index_group_name": "Baby/Children",
        "section_no": "45",
        "section_name": "Kids Outerwear",
        "garment_group_no": "1019",
        "garment_group_name": "Accessories",
        "detail_desc": "Hat in braided paper straw with a decorative band. Width of brim 9 cm."
    },
    {
        "article_id": "0548793002",
        "product_code": "0548793",
        "prod_name": "Dorchester solid",
        "product_type_no": "262",
        "product_type_name": "Jacket",
        "product_group_name": "Garment Upper body",
        "graphical_appearance_no": "1010016",
        "graphical_appearance_name": "Solid",
        "colour_group_code": "53",
        "colour_group_name": "Dark Pink",
        "perceived_colour_value_id": "4",
        "perceived_colour_value_name": "Dark",
        "perceived_colour_master_id": "4",
        "perceived_colour_master_name": "Pink",
        "department_no": "5262",
        "department_name": "Jacket Smart",
        "index_code": "F",
        "index_name": "Menswear",
        "index_group_no": "3",
        "index_group_name": "Menswear",
        "section_no": "31",
        "section_name": "Mens Outerwear",
        "garment_group_no": "1007",
        "garment_group_name": "Outdoor",
        "detail_desc": "Bomber jacket in woven fabric with a sheen, ribbed stand-up collar, zip down the front and appliqu\u00e9 on the chest. Pockets in the side seams, a zipped inner pocket, zipped sleeve pocket and ribbing at the cuffs. Quilted lining."
    },
    {
        "article_id": "0548837002",
        "product_code": "0548837",
        "prod_name": "Tara bling beanie",
        "product_type_no": "75",
        "product_type_name": "Hat/beanie",
        "product_group_name": "Accessories",
        "graphical_appearance_no": "1010002",
        "graphical_appearance_name": "Application/3D",
        "colour_group_code": "31",
        "colour_group_name": "Light Orange",
        "perceived_colour_value_id": "1",
        "perceived_colour_value_name": "Dusty Light",
        "perceived_colour_master_id": "3",
        "perceived_colour_master_name": "Orange",
        "department_no": "3945",
        "department_name": "Knit & Woven",
        "index_code": "D",
        "index_name": "Divided",
        "index_group_no": "2",
        "index_group_name": "Divided",
        "section_no": "52",
        "section_name": "Divided Accessories",
        "garment_group_no": "1019",
        "garment_group_name": "Accessories",
        "detail_desc": "Double-layered hat in a soft rib knit with sparkly stones and a sewn-in turned-up hem."
    },
    {
        "article_id": "0548869002",
        "product_code": "0548869",
        "prod_name": "Zazza blouse",
        "product_type_no": "258",
        "product_type_name": "Blouse",
        "product_group_name": "Garment Upper body",
        "graphical_appearance_no": "1010004",
        "graphical_appearance_name": "Check",
        "colour_group_code": "09",
        "colour_group_name": "Black",
        "perceived_colour_value_id": "4",
        "perceived_colour_value_name": "Dark",
        "perceived_colour_master_id": "5",
        "perceived_colour_master_name": "Black",
        "department_no": "1510",
        "department_name": "Blouse",
        "index_code": "A",
        "index_name": "Ladieswear",
        "index_group_no": "1",
        "index_group_name": "Ladieswear",
        "section_no": "6",
        "section_name": "Womens Casual",
        "garment_group_no": "1010",
        "garment_group_name": "Blouses",
        "detail_desc": "Wide, checked blouse in soft viscose flannel with a V-neck and long, wide raglan sleeves with buttoned cuffs. Rounded hem, longer at the back."
    },
    {
        "article_id": "0548879001",
        "product_code": "0548879",
        "prod_name": "Heatwave Dress_",
        "product_type_no": "265",
        "product_type_name": "Dress",
        "product_group_name": "Garment Full body",
        "graphical_appearance_no": "1010016",
        "graphical_appearance_name": "Solid",
        "colour_group_code": "71",
        "colour_group_name": "Light Blue",
        "perceived_colour_value_id": "1",
        "perceived_colour_value_name": "Dusty Light",
        "perceived_colour_master_id": "2",
        "perceived_colour_master_name": "Blue",
        "department_no": "1926",
        "department_name": "Woven Occasion",
        "index_code": "A",
        "index_name": "Ladieswear",
        "index_group_no": "1",
        "index_group_name": "Ladieswear",
        "section_no": "14",
        "section_name": "Womens Premium",
        "garment_group_no": "1013",
        "garment_group_name": "Dresses Ladies",
        "detail_desc": "Knee-length, V-neck dress in satin with short, wide sleeves. Seam at the waist with a double drawstring and slits in the sides."
    },
    {
        "article_id": "0548926001",
        "product_code": "0548926",
        "prod_name": "Sirpa twist",
        "product_type_no": "252",
        "product_type_name": "Sweater",
        "product_group_name": "Garment Upper body",
        "graphical_appearance_no": "1010010",
        "graphical_appearance_name": "Melange",
        "colour_group_code": "09",
        "colour_group_name": "Black",
        "perceived_colour_value_id": "4",
        "perceived_colour_value_name": "Dark",
        "perceived_colour_master_id": "5",
        "perceived_colour_master_name": "Black",
        "department_no": "1647",
        "department_name": "Tops Knitwear",
        "index_code": "D",
        "index_name": "Divided",
        "index_group_no": "2",
        "index_group_name": "Divided",
        "section_no": "53",
        "section_name": "Divided Collection",
        "garment_group_no": "1003",
        "garment_group_name": "Knitwear",
        "detail_desc": "Long-sleeved jumper in a soft knit with ribbing around the neckline, cuffs and hem."
    },
    {
        "article_id": "0548926003",
        "product_code": "0548926",
        "prod_name": "Sirpa twist",
        "product_type_no": "252",
        "product_type_name": "Sweater",
        "product_group_name": "Garment Upper body",
        "graphical_appearance_no": "1010010",
        "graphical_appearance_name": "Melange",
        "colour_group_code": "73",
        "colour_group_name": "Dark Blue",
        "perceived_colour_value_id": "4",
        "perceived_colour_value_name": "Dark",
        "perceived_colour_master_id": "2",
        "perceived_colour_master_name": "Blue",
        "department_no": "1647",
        "department_name": "Tops Knitwear",
        "index_code": "D",
        "index_name": "Divided",
        "index_group_no": "2",
        "index_group_name": "Divided",
        "section_no": "53",
        "section_name": "Divided Collection",
        "garment_group_no": "1003",
        "garment_group_name": "Knitwear",
        "detail_desc": "Long-sleeved jumper in a soft knit with ribbing around the neckline, cuffs and hem."
    },
    {
        "article_id": "0548930001",
        "product_code": "0548930",
        "prod_name": "Virgil cotton shirt",
        "product_type_no": "259",
        "product_type_name": "Shirt",
        "product_group_name": "Garment Upper body",
        "graphical_appearance_no": "1010001",
        "graphical_appearance_name": "All over pattern",
        "colour_group_code": "72",
        "colour_group_name": "Blue",
        "perceived_colour_value_id": "1",
        "perceived_colour_value_name": "Dusty Light",
        "perceived_colour_master_id": "2",
        "perceived_colour_master_name": "Blue",
        "department_no": "1909",
        "department_name": "Woven top",
        "index_code": "A",
        "index_name": "Ladieswear",
        "index_group_no": "1",
        "index_group_name": "Ladieswear",
        "section_no": "2",
        "section_name": "H&M+",
        "garment_group_no": "1010",
        "garment_group_name": "Blouses",
        "detail_desc": "Straight-cut shirt in a cotton weave with a collar and buttons down the front and at the cuffs. Yoke with a pleat at the back and a rounded hem."
    },
    {
        "article_id": "0548930002",
        "product_code": "0548930",
        "prod_name": "Virgil cotton shirt",
        "product_type_no": "259",
        "product_type_name": "Shirt",
        "product_group_name": "Garment Upper body",
        "graphical_appearance_no": "1010017",
        "graphical_appearance_name": "Stripe",
        "colour_group_code": "73",
        "colour_group_name": "Dark Blue",
        "perceived_colour_value_id": "5",
        "perceived_colour_value_name": "Bright",
        "perceived_colour_master_id": "2",
        "perceived_colour_master_name": "Blue",
        "department_no": "1909",
        "department_name": "Woven top",
        "index_code": "A",
        "index_name": "Ladieswear",
        "index_group_no": "1",
        "index_group_name": "Ladieswear",
        "section_no": "2",
        "section_name": "H&M+",
        "garment_group_no": "1010",
        "garment_group_name": "Blouses",
        "detail_desc": "Straight-cut shirt in a cotton weave with a collar and buttons down the front and at the cuffs. Yoke with a pleat at the back and a rounded hem."
    },
    {
        "article_id": "0548930003",
        "product_code": "0548930",
        "prod_name": "Virgil cotton shirt",
        "product_type_no": "259",
        "product_type_name": "Shirt",
        "product_group_name": "Garment Upper body",
        "graphical_appearance_no": "1010017",
        "graphical_appearance_name": "Stripe",
        "colour_group_code": "92",
        "colour_group_name": "Green",
        "perceived_colour_value_id": "5",
        "perceived_colour_value_name": "Bright",
        "perceived_colour_master_id": "19",
        "perceived_colour_master_name": "Green",
        "department_no": "1909",
        "department_name": "Woven top",
        "index_code": "A",
        "index_name": "Ladieswear",
        "index_group_no": "1",
        "index_group_name": "Ladieswear",
        "section_no": "2",
        "section_name": "H&M+",
        "garment_group_no": "1010",
        "garment_group_name": "Blouses",
        "detail_desc": "Straight-cut shirt in a cotton weave with a collar and buttons down the front and at the cuffs. Yoke with a pleat at the back and a rounded hem."
    },
    {
        "article_id": "0548930006",
        "product_code": "0548930",
        "prod_name": "Virgil cotton shirt",
        "product_type_no": "259",
        "product_type_name": "Shirt",
        "product_group_name": "Garment Upper body",
        "graphical_appearance_no": "1010004",
        "graphical_appearance_name": "Check",
        "colour_group_code": "50",
        "colour_group_name": "Other Pink",
        "perceived_colour_value_id": "5",
        "perceived_colour_value_name": "Bright",
        "perceived_colour_master_id": "4",
        "perceived_colour_master_name": "Pink",
        "department_no": "1909",
        "department_name": "Woven top",
        "index_code": "A",
        "index_name": "Ladieswear",
        "index_group_no": "1",
        "index_group_name": "Ladieswear",
        "section_no": "2",
        "section_name": "H&M+",
        "garment_group_no": "1010",
        "garment_group_name": "Blouses",
        "detail_desc": "Straight-cut shirt in a cotton weave with a collar and buttons down the front and at the cuffs. Yoke with a pleat at the back and a rounded hem."
    },
    {
        "article_id": "0548930012",
        "product_code": "0548930",
        "prod_name": "Virgil cotton shirt",
        "product_type_no": "259",
        "product_type_name": "Shirt",
        "product_group_name": "Garment Upper body",
        "graphical_appearance_no": "1010016",
        "graphical_appearance_name": "Solid",
        "colour_group_code": "10",
        "colour_group_name": "White",
        "perceived_colour_value_id": "3",
        "perceived_colour_value_name": "Light",
        "perceived_colour_master_id": "9",
        "perceived_colour_master_name": "White",
        "department_no": "1909",
        "department_name": "Woven top",
        "index_code": "A",
        "index_name": "Ladieswear",
        "index_group_no": "1",
        "index_group_name": "Ladieswear",
        "section_no": "2",
        "section_name": "H&M+",
        "garment_group_no": "1010",
        "garment_group_name": "Blouses",
        "detail_desc": "Straight-cut shirt in a cotton weave with a collar and buttons down the front and at the cuffs. Yoke with a pleat at the back and a rounded hem."
    },
    {
        "article_id": "0548930018",
        "product_code": "0548930",
        "prod_name": "Virgil cotton shirt",
        "product_type_no": "259",
        "product_type_name": "Shirt",
        "product_group_name": "Garment Upper body",
        "graphical_appearance_no": "1010001",
        "graphical_appearance_name": "All over pattern",
        "colour_group_code": "72",
        "colour_group_name": "Blue",
        "perceived_colour_value_id": "1",
        "perceived_colour_value_name": "Dusty Light",
        "perceived_colour_master_id": "2",
        "perceived_colour_master_name": "Blue",
        "department_no": "1909",
        "department_name": "Woven top",
        "index_code": "A",
        "index_name": "Ladieswear",
        "index_group_no": "1",
        "index_group_name": "Ladieswear",
        "section_no": "2",
        "section_name": "H&M+",
        "garment_group_no": "1010",
        "garment_group_name": "Blouses",
        "detail_desc": "Straight-cut shirt in a cotton weave with a collar and buttons down the front and at the cuffs. Yoke with a pleat at the back and a rounded hem."
    },
    {
        "article_id": "0548930019",
        "product_code": "0548930",
        "prod_name": "Virgil cotton shirt",
        "product_type_no": "259",
        "product_type_name": "Shirt",
        "product_group_name": "Garment Upper body",
        "graphical_appearance_no": "1010001",
        "graphical_appearance_name": "All over pattern",
        "colour_group_code": "72",
        "colour_group_name": "Blue",
        "perceived_colour_value_id": "1",
        "perceived_colour_value_name": "Dusty Light",
        "perceived_colour_master_id": "2",
        "perceived_colour_master_name": "Blue",
        "department_no": "1909",
        "department_name": "Woven top",
        "index_code": "A",
        "index_name": "Ladieswear",
        "index_group_no": "1",
        "index_group_name": "Ladieswear",
        "section_no": "2",
        "section_name": "H&M+",
        "garment_group_no": "1010",
        "garment_group_name": "Blouses",
        "detail_desc": "Straight-cut shirt in a cotton weave with a collar and buttons down the front and at the cuffs. Yoke with a pleat at the back and a rounded hem."
    },
    {
        "article_id": "0548932002",
        "product_code": "0548932",
        "prod_name": "Elie shelltop woven",
        "product_type_no": "258",
        "product_type_name": "Blouse",
        "product_group_name": "Garment Upper body",
        "graphical_appearance_no": "1010001",
        "graphical_appearance_name": "All over pattern",
        "colour_group_code": "71",
        "colour_group_name": "Light Blue",
        "perceived_colour_value_id": "1",
        "perceived_colour_value_name": "Dusty Light",
        "perceived_colour_master_id": "2",
        "perceived_colour_master_name": "Blue",
        "department_no": "1909",
        "department_name": "Woven top",
        "index_code": "A",
        "index_name": "Ladieswear",
        "index_group_no": "1",
        "index_group_name": "Ladieswear",
        "section_no": "2",
        "section_name": "H&M+",
        "garment_group_no": "1010",
        "garment_group_name": "Blouses",
        "detail_desc": "Short-sleeved top in viscose cr\u00eape with a round neckline and a rounded hem. Slightly longer at the back."
    },
    {
        "article_id": "0548932005",
        "product_code": "0548932",
        "prod_name": "ED Syrup shelltop",
        "product_type_no": "258",
        "product_type_name": "Blouse",
        "product_group_name": "Garment Upper body",
        "graphical_appearance_no": "1010001",
        "graphical_appearance_name": "All over pattern",
        "colour_group_code": "10",
        "colour_group_name": "White",
        "perceived_colour_value_id": "3",
        "perceived_colour_value_name": "Light",
        "perceived_colour_master_id": "9",
        "perceived_colour_master_name": "White",
        "department_no": "1909",
        "department_name": "Woven top",
        "index_code": "A",
        "index_name": "Ladieswear",
        "index_group_no": "1",
        "index_group_name": "Ladieswear",
        "section_no": "2",
        "section_name": "H&M+",
        "garment_group_no": "1010",
        "garment_group_name": "Blouses",
        "detail_desc": "Short-sleeved top in viscose cr\u00eape with a round neckline and a rounded hem. Slightly longer at the back."
    },
    {
        "article_id": "0548932006",
        "product_code": "0548932",
        "prod_name": "ED Syrup shelltop",
        "product_type_no": "258",
        "product_type_name": "Blouse",
        "product_group_name": "Garment Upper body",
        "graphical_appearance_no": "1010001",
        "graphical_appearance_name": "All over pattern",
        "colour_group_code": "73",
        "colour_group_name": "Dark Blue",
        "perceived_colour_value_id": "4",
        "perceived_colour_value_name": "Dark",
        "perceived_colour_master_id": "2",
        "perceived_colour_master_name": "Blue",
        "department_no": "1909",
        "department_name": "Woven top",
        "index_code": "A",
        "index_name": "Ladieswear",
        "index_group_no": "1",
        "index_group_name": "Ladieswear",
        "section_no": "2",
        "section_name": "H&M+",
        "garment_group_no": "1010",
        "garment_group_name": "Blouses",
        "detail_desc": "Short-sleeved top in viscose cr\u00eape with a round neckline and a rounded hem. Slightly longer at the back."
    },
    {
        "article_id": "0548932008",
        "product_code": "0548932",
        "prod_name": "ED Syrup shelltop",
        "product_type_no": "258",
        "product_type_name": "Blouse",
        "product_group_name": "Garment Upper body",
        "graphical_appearance_no": "1010016",
        "graphical_appearance_name": "Solid",
        "colour_group_code": "93",
        "colour_group_name": "Dark Green",
        "perceived_colour_value_id": "4",
        "perceived_colour_value_name": "Dark",
        "perceived_colour_master_id": "19",
        "perceived_colour_master_name": "Green",
        "department_no": "1909",
        "department_name": "Woven top",
        "index_code": "A",
        "index_name": "Ladieswear",
        "index_group_no": "1",
        "index_group_name": "Ladieswear",
        "section_no": "2",
        "section_name": "H&M+",
        "garment_group_no": "1010",
        "garment_group_name": "Blouses",
        "detail_desc": "Short-sleeved top in viscose cr\u00eape with a round neckline and a rounded hem. Slightly longer at the back."
    },
    {
        "article_id": "0548946001",
        "product_code": "0548946",
        "prod_name": "Sunshine blouse",
        "product_type_no": "258",
        "product_type_name": "Blouse",
        "product_group_name": "Garment Upper body",
        "graphical_appearance_no": "1010007",
        "graphical_appearance_name": "Embroidery",
        "colour_group_code": "09",
        "colour_group_name": "Black",
        "perceived_colour_value_id": "4",
        "perceived_colour_value_name": "Dark",
        "perceived_colour_master_id": "5",
        "perceived_colour_master_name": "Black",
        "department_no": "1909",
        "department_name": "Woven top",
        "index_code": "A",
        "index_name": "Ladieswear",
        "index_group_no": "1",
        "index_group_name": "Ladieswear",
        "section_no": "2",
        "section_name": "H&M+",
        "garment_group_no": "1010",
        "garment_group_name": "Blouses",
        "detail_desc": "Blouse in a cotton weave with broderie anglaise. Scallop-edged round neck with an opening and button at the back and long, trumpet sleeves. Unlined."
    },
    {
        "article_id": "0548947001",
        "product_code": "0548947",
        "prod_name": "Aztec blouse",
        "product_type_no": "254",
        "product_type_name": "Top",
        "product_group_name": "Garment Upper body",
        "graphical_appearance_no": "1010001",
        "graphical_appearance_name": "All over pattern",
        "colour_group_code": "11",
        "colour_group_name": "Off White",
        "perceived_colour_value_id": "1",
        "perceived_colour_value_name": "Dusty Light",
        "perceived_colour_master_id": "9",
        "perceived_colour_master_name": "White",
        "department_no": "1909",
        "department_name": "Woven top",
        "index_code": "A",
        "index_name": "Ladieswear",
        "index_group_no": "1",
        "index_group_name": "Ladieswear",
        "section_no": "2",
        "section_name": "H&M+",
        "garment_group_no": "1010",
        "garment_group_name": "Blouses",
        "detail_desc": "Blouse in a patterned viscose weave with a stand-up collar, covered buttons at the top and a gathered yoke. Long sleeves with cuffs and covered buttons."
    },
    {
        "article_id": "0548963001",
        "product_code": "0548963",
        "prod_name": "ED freshqueen off shoulder",
        "product_type_no": "258",
        "product_type_name": "Blouse",
        "product_group_name": "Garment Upper body",
        "graphical_appearance_no": "1010017",
        "graphical_appearance_name": "Stripe",
        "colour_group_code": "72",
        "colour_group_name": "Blue",
        "perceived_colour_value_id": "7",
        "perceived_colour_value_name": "Medium",
        "perceived_colour_master_id": "2",
        "perceived_colour_master_name": "Blue",
        "department_no": "1909",
        "department_name": "Woven top",
        "index_code": "A",
        "index_name": "Ladieswear",
        "index_group_no": "1",
        "index_group_name": "Ladieswear",
        "section_no": "2",
        "section_name": "H&M+",
        "garment_group_no": "1010",
        "garment_group_name": "Blouses",
        "detail_desc": "Off-the-shoulder top in a viscose weave with elastication and a flounce at the top, 3/4-length sleeves with a slit and tie detail at the cuffs, and a rounded hem."
    },
    {
        "article_id": "0548964001",
        "product_code": "0548964",
        "prod_name": "Elliot dress",
        "product_type_no": "258",
        "product_type_name": "Blouse",
        "product_group_name": "Garment Upper body",
        "graphical_appearance_no": "1010001",
        "graphical_appearance_name": "All over pattern",
        "colour_group_code": "09",
        "colour_group_name": "Black",
        "perceived_colour_value_id": "4",
        "perceived_colour_value_name": "Dark",
        "perceived_colour_master_id": "5",
        "perceived_colour_master_name": "Black",
        "department_no": "1909",
        "department_name": "Woven top",
        "index_code": "A",
        "index_name": "Ladieswear",
        "index_group_no": "1",
        "index_group_name": "Ladieswear",
        "section_no": "2",
        "section_name": "H&M+",
        "garment_group_no": "1010",
        "garment_group_name": "Blouses",
        "detail_desc": "Straight-cut dress in a soft, patterned weave with a wide neckline, long sleeves and softly draped front. Wide, sewn-on tie belt at the waist. Unlined."
    },
    {
        "article_id": "0548966002",
        "product_code": "0548966",
        "prod_name": "ED Rose dress",
        "product_type_no": "265",
        "product_type_name": "Dress",
        "product_group_name": "Garment Full body",
        "graphical_appearance_no": "1010001",
        "graphical_appearance_name": "All over pattern",
        "colour_group_code": "73",
        "colour_group_name": "Dark Blue",
        "perceived_colour_value_id": "4",
        "perceived_colour_value_name": "Dark",
        "perceived_colour_master_id": "2",
        "perceived_colour_master_name": "Blue",
        "department_no": "1909",
        "department_name": "Woven top",
        "index_code": "A",
        "index_name": "Ladieswear",
        "index_group_no": "1",
        "index_group_name": "Ladieswear",
        "section_no": "2",
        "section_name": "H&M+",
        "garment_group_no": "1010",
        "garment_group_name": "Blouses",
        "detail_desc": "Knee-length dress in an airy, patterned viscose weave in a straight cut with half-length sleeves that are open at the top with ties at the cuffs. Unlined."
    },
    {
        "article_id": "0548967001",
        "product_code": "0548967",
        "prod_name": "Badu lace blouse",
        "product_type_no": "254",
        "product_type_name": "Top",
        "product_group_name": "Garment Upper body",
        "graphical_appearance_no": "1010021",
        "graphical_appearance_name": "Lace",
        "colour_group_code": "09",
        "colour_group_name": "Black",
        "perceived_colour_value_id": "4",
        "perceived_colour_value_name": "Dark",
        "perceived_colour_master_id": "5",
        "perceived_colour_master_name": "Black",
        "department_no": "1909",
        "department_name": "Woven top",
        "index_code": "A",
        "index_name": "Ladieswear",
        "index_group_no": "1",
        "index_group_name": "Ladieswear",
        "section_no": "2",
        "section_name": "H&M+",
        "garment_group_no": "1010",
        "garment_group_name": "Blouses",
        "detail_desc": "Lace blouse with a stand-up collar, opening with a concealed button at the back of the neck and long sleeves with frilled cuffs. Lined with a jersey top with narrow shoulder straps."
    },
    {
        "article_id": "0548968001",
        "product_code": "0548968",
        "prod_name": "Aloha shirt",
        "product_type_no": "258",
        "product_type_name": "Blouse",
        "product_group_name": "Garment Upper body",
        "graphical_appearance_no": "1010007",
        "graphical_appearance_name": "Embroidery",
        "colour_group_code": "83",
        "colour_group_name": "Dark Turquoise",
        "perceived_colour_value_id": "5",
        "perceived_colour_value_name": "Bright",
        "perceived_colour_master_id": "7",
        "perceived_colour_master_name": "Turquoise",
        "department_no": "1909",
        "department_name": "Woven top",
        "index_code": "A",
        "index_name": "Ladieswear",
        "index_group_no": "1",
        "index_group_name": "Ladieswear",
        "section_no": "2",
        "section_name": "H&M+",
        "garment_group_no": "1010",
        "garment_group_name": "Blouses",
        "detail_desc": "Blouse in a patterned viscose weave with a collar and concealed buttons down the front. Yoke with a pleat at the back, wide, 3/4-length sleeves and a rounded hem."
    },
    {
        "article_id": "0548969001",
        "product_code": "0548969",
        "prod_name": "ED coco sleeveless TRIS",
        "product_type_no": "258",
        "product_type_name": "Blouse",
        "product_group_name": "Garment Upper body",
        "graphical_appearance_no": "1010001",
        "graphical_appearance_name": "All over pattern",
        "colour_group_code": "10",
        "colour_group_name": "White",
        "perceived_colour_value_id": "3",
        "perceived_colour_value_name": "Light",
        "perceived_colour_master_id": "9",
        "perceived_colour_master_name": "White",
        "department_no": "1909",
        "department_name": "Woven top",
        "index_code": "A",
        "index_name": "Ladieswear",
        "index_group_no": "1",
        "index_group_name": "Ladieswear",
        "section_no": "2",
        "section_name": "H&M+",
        "garment_group_no": "1010",
        "garment_group_name": "Blouses",
        "detail_desc": "Sleeveless blouse in an airy, patterned weave with a collar, buttons down the front, yoke with a pleat at the back and a rounded hem. Slightly longer at the back."
    },
    {
        "article_id": "0548971001",
        "product_code": "0548971",
        "prod_name": "Timbaland dress",
        "product_type_no": "265",
        "product_type_name": "Dress",
        "product_group_name": "Garment Full body",
        "graphical_appearance_no": "1010001",
        "graphical_appearance_name": "All over pattern",
        "colour_group_code": "41",
        "colour_group_name": "Light Red",
        "perceived_colour_value_id": "5",
        "perceived_colour_value_name": "Bright",
        "perceived_colour_master_id": "18",
        "perceived_colour_master_name": "Red",
        "department_no": "1909",
        "department_name": "Woven top",
        "index_code": "A",
        "index_name": "Ladieswear",
        "index_group_no": "1",
        "index_group_name": "Ladieswear",
        "section_no": "2",
        "section_name": "H&M+",
        "garment_group_no": "1010",
        "garment_group_name": "Blouses",
        "detail_desc": "Short, straight-cut dress in an airy, patterned weave with a V-neck and 3/4-length sleeves with a flounce at the cuffs. Unlined."
    },
    {
        "article_id": "0548978001",
        "product_code": "0548978",
        "prod_name": "P Liv nursing dress",
        "product_type_no": "265",
        "product_type_name": "Dress",
        "product_group_name": "Garment Full body",
        "graphical_appearance_no": "1010016",
        "graphical_appearance_name": "Solid",
        "colour_group_code": "09",
        "colour_group_name": "Black",
        "perceived_colour_value_id": "4",
        "perceived_colour_value_name": "Dark",
        "perceived_colour_master_id": "5",
        "perceived_colour_master_name": "Black",
        "department_no": "2035",
        "department_name": "Nursing",
        "index_code": "A",
        "index_name": "Ladieswear",
        "index_group_no": "1",
        "index_group_name": "Ladieswear",
        "section_no": "8",
        "section_name": "Mama",
        "garment_group_no": "1005",
        "garment_group_name": "Jersey Fancy",
        "detail_desc": "Dress in soft jersey with a unique nursing feature. The dress is fitted, knee-length and has 3/4-length sleeves. The design includes a double layer at the top to help you keep warm while allowing easy access to the bust for nursing."
    },
    {
        "article_id": "0548986001",
        "product_code": "0548986",
        "prod_name": "Oprah skirt",
        "product_type_no": "275",
        "product_type_name": "Skirt",
        "product_group_name": "Garment Lower body",
        "graphical_appearance_no": "1010016",
        "graphical_appearance_name": "Solid",
        "colour_group_code": "19",
        "colour_group_name": "Greenish Khaki",
        "perceived_colour_value_id": "2",
        "perceived_colour_value_name": "Medium Dusty",
        "perceived_colour_master_id": "20",
        "perceived_colour_master_name": "Khaki green",
        "department_no": "1410",
        "department_name": "Shorts & Skirts",
        "index_code": "A",
        "index_name": "Ladieswear",
        "index_group_no": "1",
        "index_group_name": "Ladieswear",
        "section_no": "6",
        "section_name": "Womens Casual",
        "garment_group_no": "1025",
        "garment_group_name": "Shorts",
        "detail_desc": "Short skirt in soft twill made from Tencel\u2122 lyocell with an elasticated drawstring waist and side pockets. Rounded hem with short slits in the sides. Unlined."
    },
    {
        "article_id": "0549024002",
        "product_code": "0549024",
        "prod_name": "Filippa scarf",
        "product_type_no": "80",
        "product_type_name": "Scarf",
        "product_group_name": "Accessories",
        "graphical_appearance_no": "1010005",
        "graphical_appearance_name": "Colour blocking",
        "colour_group_code": "53",
        "colour_group_name": "Dark Pink",
        "perceived_colour_value_id": "5",
        "perceived_colour_value_name": "Bright",
        "perceived_colour_master_id": "4",
        "perceived_colour_master_name": "Pink",
        "department_no": "3945",
        "department_name": "Knit & Woven",
        "index_code": "D",
        "index_name": "Divided",
        "index_group_no": "2",
        "index_group_name": "Divided",
        "section_no": "52",
        "section_name": "Divided Accessories",
        "garment_group_no": "1019",
        "garment_group_name": "Accessories",
        "detail_desc": "Scarf in a soft weave with a brushed finish. Fringes on the short sides. Size 65x195 cm."
    },
    {
        "article_id": "0549090001",
        "product_code": "0549090",
        "prod_name": "D. Steve Atellier wash",
        "product_type_no": "272",
        "product_type_name": "Trousers",
        "product_group_name": "Garment Lower body",
        "graphical_appearance_no": "1010023",
        "graphical_appearance_name": "Denim",
        "colour_group_code": "73",
        "colour_group_name": "Dark Blue",
        "perceived_colour_value_id": "2",
        "perceived_colour_value_name": "Medium Dusty",
        "perceived_colour_master_id": "2",
        "perceived_colour_master_name": "Blue",
        "department_no": "5656",
        "department_name": "Trouser",
        "index_code": "F",
        "index_name": "Menswear",
        "index_group_no": "3",
        "index_group_name": "Menswear",
        "section_no": "21",
        "section_name": "Contemporary Casual",
        "garment_group_no": "1009",
        "garment_group_name": "Trousers",
        "detail_desc": "5-pocket jeans in washed denim with a regular waist, button fly and straight legs."
    },
    {
        "article_id": "0549108001",
        "product_code": "0549108",
        "prod_name": "morpheus midwash",
        "product_type_no": "262",
        "product_type_name": "Jacket",
        "product_group_name": "Garment Upper body",
        "graphical_appearance_no": "1010023",
        "graphical_appearance_name": "Denim",
        "colour_group_code": "72",
        "colour_group_name": "Blue",
        "perceived_colour_value_id": "2",
        "perceived_colour_value_name": "Medium Dusty",
        "perceived_colour_master_id": "2",
        "perceived_colour_master_name": "Blue",
        "department_no": "1779",
        "department_name": "Everyday Waredrobe Denim",
        "index_code": "A",
        "index_name": "Ladieswear",
        "index_group_no": "1",
        "index_group_name": "Ladieswear",
        "section_no": "57",
        "section_name": "Ladies Denim",
        "garment_group_no": "1016",
        "garment_group_name": "Trousers Denim",
        "detail_desc": "Jacket in washed denim with a collar, buttons down the front and at the cuffs, flap chest pockets with a button, welt side pockets and adjustable tab and buttons at the sides."
    },
    {
        "article_id": "0549113001",
        "product_code": "0549113",
        "prod_name": "Queen Bee Leo",
        "product_type_no": "262",
        "product_type_name": "Jacket",
        "product_group_name": "Garment Upper body",
        "graphical_appearance_no": "1010001",
        "graphical_appearance_name": "All over pattern",
        "colour_group_code": "09",
        "colour_group_name": "Black",
        "perceived_colour_value_id": "4",
        "perceived_colour_value_name": "Dark",
        "perceived_colour_master_id": "5",
        "perceived_colour_master_name": "Black",
        "department_no": "1244",
        "department_name": "Outdoor/Blazers",
        "index_code": "D",
        "index_name": "Divided",
        "index_group_no": "2",
        "index_group_name": "Divided",
        "section_no": "53",
        "section_name": "Divided Collection",
        "garment_group_no": "1007",
        "garment_group_name": "Outdoor",
        "detail_desc": "Collarless, round-necked coat in soft faux fur with concealed press-studs down the front and pockets in the side seams. Lined."
    },
    {
        "article_id": "0549131001",
        "product_code": "0549131",
        "prod_name": "W Hay",
        "product_type_no": "275",
        "product_type_name": "Skirt",
        "product_group_name": "Garment Lower body",
        "graphical_appearance_no": "1010001",
        "graphical_appearance_name": "All over pattern",
        "colour_group_code": "13",
        "colour_group_name": "Beige",
        "perceived_colour_value_id": "2",
        "perceived_colour_value_name": "Medium Dusty",
        "perceived_colour_master_id": "11",
        "perceived_colour_master_name": "Beige",
        "department_no": "1422",
        "department_name": "Skirt",
        "index_code": "A",
        "index_name": "Ladieswear",
        "index_group_no": "1",
        "index_group_name": "Ladieswear",
        "section_no": "15",
        "section_name": "Womens Everyday Collection",
        "garment_group_no": "1012",
        "garment_group_name": "Skirts",
        "detail_desc": "Pleated skirt in woven fabric with a concealed zip and hook-and-eye fastener in the side."
    },
    {
        "article_id": "0549135001",
        "product_code": "0549135",
        "prod_name": "W Cassidy",
        "product_type_no": "275",
        "product_type_name": "Skirt",
        "product_group_name": "Garment Lower body",
        "graphical_appearance_no": "1010016",
        "graphical_appearance_name": "Solid",
        "colour_group_code": "03",
        "colour_group_name": "Silver",
        "perceived_colour_value_id": "3",
        "perceived_colour_value_name": "Light",
        "perceived_colour_master_id": "15",
        "perceived_colour_master_name": "Metal",
        "department_no": "1422",
        "department_name": "Skirt",
        "index_code": "A",
        "index_name": "Ladieswear",
        "index_group_no": "1",
        "index_group_name": "Ladieswear",
        "section_no": "15",
        "section_name": "Womens Everyday Collection",
        "garment_group_no": "1012",
        "garment_group_name": "Skirts",
        "detail_desc": "Short skirt in imitation leather with a shimmering metallic finish and visible zip at the back. Lined."
    },
    {
        "article_id": "0549148010",
        "product_code": "0549148",
        "prod_name": "Csp lavender",
        "product_type_no": "254",
        "product_type_name": "Top",
        "product_group_name": "Garment Upper body",
        "graphical_appearance_no": "1010002",
        "graphical_appearance_name": "Application/3D",
        "colour_group_code": "07",
        "colour_group_name": "Grey",
        "perceived_colour_value_id": "1",
        "perceived_colour_value_name": "Dusty Light",
        "perceived_colour_master_id": "12",
        "perceived_colour_master_name": "Grey",
        "department_no": "1636",
        "department_name": "Jersey fancy",
        "index_code": "A",
        "index_name": "Ladieswear",
        "index_group_no": "1",
        "index_group_name": "Ladieswear",
        "section_no": "15",
        "section_name": "Womens Everyday Collection",
        "garment_group_no": "1005",
        "garment_group_name": "Jersey Fancy",
        "detail_desc": "T-shirt in soft jersey with embroidered appliqu\u00e9s."
    },
    {
        "article_id": "0549164002",
        "product_code": "0549164",
        "prod_name": "Maxime blouse",
        "product_type_no": "258",
        "product_type_name": "Blouse",
        "product_group_name": "Garment Upper body",
        "graphical_appearance_no": "1010016",
        "graphical_appearance_name": "Solid",
        "colour_group_code": "09",
        "colour_group_name": "Black",
        "perceived_colour_value_id": "4",
        "perceived_colour_value_name": "Dark",
        "perceived_colour_master_id": "5",
        "perceived_colour_master_name": "Black",
        "department_no": "1543",
        "department_name": "Tops Woven",
        "index_code": "D",
        "index_name": "Divided",
        "index_group_no": "2",
        "index_group_name": "Divided",
        "section_no": "53",
        "section_name": "Divided Collection",
        "garment_group_no": "1010",
        "garment_group_name": "Blouses",
        "detail_desc": "Cold shoulder top in an airy weave with an opening and button at the back of the neck, lace yoke, flounce at the top and long sleeves with narrow elastication and a flounce at the cuffs."
    },
    {
        "article_id": "0549243002",
        "product_code": "0549243",
        "prod_name": "Ivan",
        "product_type_no": "254",
        "product_type_name": "Top",
        "product_group_name": "Garment Upper body",
        "graphical_appearance_no": "1010016",
        "graphical_appearance_name": "Solid",
        "colour_group_code": "09",
        "colour_group_name": "Black",
        "perceived_colour_value_id": "4",
        "perceived_colour_value_name": "Dark",
        "perceived_colour_master_id": "5",
        "perceived_colour_master_name": "Black",
        "department_no": "1636",
        "department_name": "Jersey fancy",
        "index_code": "A",
        "index_name": "Ladieswear",
        "index_group_no": "1",
        "index_group_name": "Ladieswear",
        "section_no": "15",
        "section_name": "Womens Everyday Collection",
        "garment_group_no": "1005",
        "garment_group_name": "Jersey Fancy",
        "detail_desc": "Sheer jersey top in a narrow cut at the top with lace at the back, narrow shoulder straps and an opening with a button at the back of the neck."
    },
    {
        "article_id": "0549243003",
        "product_code": "0549243",
        "prod_name": "Ivan",
        "product_type_no": "254",
        "product_type_name": "Top",
        "product_group_name": "Garment Upper body",
        "graphical_appearance_no": "1010016",
        "graphical_appearance_name": "Solid",
        "colour_group_code": "43",
        "colour_group_name": "Dark Red",
        "perceived_colour_value_id": "4",
        "perceived_colour_value_name": "Dark",
        "perceived_colour_master_id": "18",
        "perceived_colour_master_name": "Red",
        "department_no": "1636",
        "department_name": "Jersey fancy",
        "index_code": "A",
        "index_name": "Ladieswear",
        "index_group_no": "1",
        "index_group_name": "Ladieswear",
        "section_no": "15",
        "section_name": "Womens Everyday Collection",
        "garment_group_no": "1005",
        "garment_group_name": "Jersey Fancy",
        "detail_desc": "Sheer jersey top in a narrow cut at the top with lace at the back, narrow shoulder straps and an opening with a button at the back of the neck."
    },
    {
        "article_id": "0549251001",
        "product_code": "0549251",
        "prod_name": "Sanne treggings",
        "product_type_no": "272",
        "product_type_name": "Trousers",
        "product_group_name": "Garment Lower body",
        "graphical_appearance_no": "1010016",
        "graphical_appearance_name": "Solid",
        "colour_group_code": "09",
        "colour_group_name": "Black",
        "perceived_colour_value_id": "4",
        "perceived_colour_value_name": "Dark",
        "perceived_colour_master_id": "5",
        "perceived_colour_master_name": "Black",
        "department_no": "1939",
        "department_name": "Woven bottoms",
        "index_code": "A",
        "index_name": "Ladieswear",
        "index_group_no": "1",
        "index_group_name": "Ladieswear",
        "section_no": "2",
        "section_name": "H&M+",
        "garment_group_no": "1009",
        "garment_group_name": "Trousers",
        "detail_desc": "Treggings in stretch twill with an elasticated waist, fake front pockets and real back pockets."
    },
    {
        "article_id": "0549251003",
        "product_code": "0549251",
        "prod_name": "Sanne treggings",
        "product_type_no": "272",
        "product_type_name": "Trousers",
        "product_group_name": "Garment Lower body",
        "graphical_appearance_no": "1010023",
        "graphical_appearance_name": "Denim",
        "colour_group_code": "08",
        "colour_group_name": "Dark Grey",
        "perceived_colour_value_id": "4",
        "perceived_colour_value_name": "Dark",
        "perceived_colour_master_id": "12",
        "perceived_colour_master_name": "Grey",
        "department_no": "1939",
        "department_name": "Woven bottoms",
        "index_code": "A",
        "index_name": "Ladieswear",
        "index_group_no": "1",
        "index_group_name": "Ladieswear",
        "section_no": "2",
        "section_name": "H&M+",
        "garment_group_no": "1009",
        "garment_group_name": "Trousers",
        "detail_desc": "Treggings in stretch twill with an elasticated waist, fake front pockets and real back pockets."
    },
    {
        "article_id": "0549251004",
        "product_code": "0549251",
        "prod_name": "Sanne treggings",
        "product_type_no": "272",
        "product_type_name": "Trousers",
        "product_group_name": "Garment Lower body",
        "graphical_appearance_no": "1010023",
        "graphical_appearance_name": "Denim",
        "colour_group_code": "72",
        "colour_group_name": "Blue",
        "perceived_colour_value_id": "2",
        "perceived_colour_value_name": "Medium Dusty",
        "perceived_colour_master_id": "2",
        "perceived_colour_master_name": "Blue",
        "department_no": "1939",
        "department_name": "Woven bottoms",
        "index_code": "A",
        "index_name": "Ladieswear",
        "index_group_no": "1",
        "index_group_name": "Ladieswear",
        "section_no": "2",
        "section_name": "H&M+",
        "garment_group_no": "1009",
        "garment_group_name": "Trousers",
        "detail_desc": "Treggings in stretch twill with an elasticated waist, fake front pockets and real back pockets."
    },
    {
        "article_id": "0549251005",
        "product_code": "0549251",
        "prod_name": "Sanne treggings",
        "product_type_no": "272",
        "product_type_name": "Trousers",
        "product_group_name": "Garment Lower body",
        "graphical_appearance_no": "1010023",
        "graphical_appearance_name": "Denim",
        "colour_group_code": "71",
        "colour_group_name": "Light Blue",
        "perceived_colour_value_id": "1",
        "perceived_colour_value_name": "Dusty Light",
        "perceived_colour_master_id": "2",
        "perceived_colour_master_name": "Blue",
        "department_no": "1939",
        "department_name": "Woven bottoms",
        "index_code": "A",
        "index_name": "Ladieswear",
        "index_group_no": "1",
        "index_group_name": "Ladieswear",
        "section_no": "2",
        "section_name": "H&M+",
        "garment_group_no": "1009",
        "garment_group_name": "Trousers",
        "detail_desc": "Treggings in stretch twill with an elasticated waist, fake front pockets and real back pockets."
    },
    {
        "article_id": "0549251012",
        "product_code": "0549251",
        "prod_name": "Sanne treggings",
        "product_type_no": "272",
        "product_type_name": "Trousers",
        "product_group_name": "Garment Lower body",
        "graphical_appearance_no": "1010023",
        "graphical_appearance_name": "Denim",
        "colour_group_code": "73",
        "colour_group_name": "Dark Blue",
        "perceived_colour_value_id": "2",
        "perceived_colour_value_name": "Medium Dusty",
        "perceived_colour_master_id": "2",
        "perceived_colour_master_name": "Blue",
        "department_no": "1939",
        "department_name": "Woven bottoms",
        "index_code": "A",
        "index_name": "Ladieswear",
        "index_group_no": "1",
        "index_group_name": "Ladieswear",
        "section_no": "2",
        "section_name": "H&M+",
        "garment_group_no": "1009",
        "garment_group_name": "Trousers",
        "detail_desc": "Treggings in stretch twill with an elasticated waist, fake front pockets and real back pockets."
    },
    {
        "article_id": "0549251013",
        "product_code": "0549251",
        "prod_name": "Sanne treggings",
        "product_type_no": "272",
        "product_type_name": "Trousers",
        "product_group_name": "Garment Lower body",
        "graphical_appearance_no": "1010023",
        "graphical_appearance_name": "Denim",
        "colour_group_code": "06",
        "colour_group_name": "Light Grey",
        "perceived_colour_value_id": "1",
        "perceived_colour_value_name": "Dusty Light",
        "perceived_colour_master_id": "12",
        "perceived_colour_master_name": "Grey",
        "department_no": "1939",
        "department_name": "Woven bottoms",
        "index_code": "A",
        "index_name": "Ladieswear",
        "index_group_no": "1",
        "index_group_name": "Ladieswear",
        "section_no": "2",
        "section_name": "H&M+",
        "garment_group_no": "1009",
        "garment_group_name": "Trousers",
        "detail_desc": "Treggings in stretch twill with an elasticated waist, fake front pockets and real back pockets."
    },
    {
        "article_id": "0549252001",
        "product_code": "0549252",
        "prod_name": "SPEED Penny tregging denim",
        "product_type_no": "272",
        "product_type_name": "Trousers",
        "product_group_name": "Garment Lower body",
        "graphical_appearance_no": "1010023",
        "graphical_appearance_name": "Denim",
        "colour_group_code": "73",
        "colour_group_name": "Dark Blue",
        "perceived_colour_value_id": "2",
        "perceived_colour_value_name": "Medium Dusty",
        "perceived_colour_master_id": "2",
        "perceived_colour_master_name": "Blue",
        "department_no": "1939",
        "department_name": "Woven bottoms",
        "index_code": "A",
        "index_name": "Ladieswear",
        "index_group_no": "1",
        "index_group_name": "Ladieswear",
        "section_no": "2",
        "section_name": "H&M+",
        "garment_group_no": "1009",
        "garment_group_name": "Trousers",
        "detail_desc": "Treggings in washed superstretch denim with hard-worn details. Elasticated waist, fake fly, fake front pockets and real back pockets."
    },
    {
        "article_id": "0549253001",
        "product_code": "0549253",
        "prod_name": "Skinny RW denim",
        "product_type_no": "272",
        "product_type_name": "Trousers",
        "product_group_name": "Garment Lower body",
        "graphical_appearance_no": "1010023",
        "graphical_appearance_name": "Denim",
        "colour_group_code": "09",
        "colour_group_name": "Black",
        "perceived_colour_value_id": "4",
        "perceived_colour_value_name": "Dark",
        "perceived_colour_master_id": "5",
        "perceived_colour_master_name": "Black",
        "department_no": "1939",
        "department_name": "Woven bottoms",
        "index_code": "A",
        "index_name": "Ladieswear",
        "index_group_no": "1",
        "index_group_name": "Ladieswear",
        "section_no": "2",
        "section_name": "H&M+",
        "garment_group_no": "1009",
        "garment_group_name": "Trousers",
        "detail_desc": "5-pocket jeans in superstretch denim with a regular waist, zip fly and button, and skinny legs."
    },
    {
        "article_id": "0549253002",
        "product_code": "0549253",
        "prod_name": "Skinny RW denim",
        "product_type_no": "272",
        "product_type_name": "Trousers",
        "product_group_name": "Garment Lower body",
        "graphical_appearance_no": "1010023",
        "graphical_appearance_name": "Denim",
        "colour_group_code": "71",
        "colour_group_name": "Light Blue",
        "perceived_colour_value_id": "1",
        "perceived_colour_value_name": "Dusty Light",
        "perceived_colour_master_id": "2",
        "perceived_colour_master_name": "Blue",
        "department_no": "1939",
        "department_name": "Woven bottoms",
        "index_code": "A",
        "index_name": "Ladieswear",
        "index_group_no": "1",
        "index_group_name": "Ladieswear",
        "section_no": "2",
        "section_name": "H&M+",
        "garment_group_no": "1009",
        "garment_group_name": "Trousers",
        "detail_desc": "5-pocket jeans in superstretch denim with a regular waist, zip fly and button, and skinny legs."
    },
    {
        "article_id": "0549253003",
        "product_code": "0549253",
        "prod_name": "Skinny RW denim",
        "product_type_no": "272",
        "product_type_name": "Trousers",
        "product_group_name": "Garment Lower body",
        "graphical_appearance_no": "1010023",
        "graphical_appearance_name": "Denim",
        "colour_group_code": "09",
        "colour_group_name": "Black",
        "perceived_colour_value_id": "4",
        "perceived_colour_value_name": "Dark",
        "perceived_colour_master_id": "5",
        "perceived_colour_master_name": "Black",
        "department_no": "1939",
        "department_name": "Woven bottoms",
        "index_code": "A",
        "index_name": "Ladieswear",
        "index_group_no": "1",
        "index_group_name": "Ladieswear",
        "section_no": "2",
        "section_name": "H&M+",
        "garment_group_no": "1009",
        "garment_group_name": "Trousers",
        "detail_desc": "5-pocket jeans in superstretch denim with a regular waist, zip fly and button, and skinny legs."
    },
    {
        "article_id": "0549253007",
        "product_code": "0549253",
        "prod_name": "Skinny RW denim",
        "product_type_no": "272",
        "product_type_name": "Trousers",
        "product_group_name": "Garment Lower body",
        "graphical_appearance_no": "1010023",
        "graphical_appearance_name": "Denim",
        "colour_group_code": "72",
        "colour_group_name": "Blue",
        "perceived_colour_value_id": "2",
        "perceived_colour_value_name": "Medium Dusty",
        "perceived_colour_master_id": "2",
        "perceived_colour_master_name": "Blue",
        "department_no": "1939",
        "department_name": "Woven bottoms",
        "index_code": "A",
        "index_name": "Ladieswear",
        "index_group_no": "1",
        "index_group_name": "Ladieswear",
        "section_no": "2",
        "section_name": "H&M+",
        "garment_group_no": "1009",
        "garment_group_name": "Trousers",
        "detail_desc": "5-pocket jeans in superstretch denim with a regular waist, zip fly and button, and skinny legs."
    },
    {
        "article_id": "0549256001",
        "product_code": "0549256",
        "prod_name": "Skinny HW tusuka buttons",
        "product_type_no": "272",
        "product_type_name": "Trousers",
        "product_group_name": "Garment Lower body",
        "graphical_appearance_no": "1010023",
        "graphical_appearance_name": "Denim",
        "colour_group_code": "73",
        "colour_group_name": "Dark Blue",
        "perceived_colour_value_id": "2",
        "perceived_colour_value_name": "Medium Dusty",
        "perceived_colour_master_id": "2",
        "perceived_colour_master_name": "Blue",
        "department_no": "1939",
        "department_name": "Woven bottoms",
        "index_code": "A",
        "index_name": "Ladieswear",
        "index_group_no": "1",
        "index_group_name": "Ladieswear",
        "section_no": "2",
        "section_name": "H&M+",
        "garment_group_no": "1009",
        "garment_group_name": "Trousers",
        "detail_desc": "High-waisted, 5-pocket jeans in stretch denim with a visible button fly and skinny legs."
    },
    {
        "article_id": "0549257001",
        "product_code": "0549257",
        "prod_name": "Linda woven trs",
        "product_type_no": "272",
        "product_type_name": "Trousers",
        "product_group_name": "Garment Lower body",
        "graphical_appearance_no": "1010016",
        "graphical_appearance_name": "Solid",
        "colour_group_code": "09",
        "colour_group_name": "Black",
        "perceived_colour_value_id": "4",
        "perceived_colour_value_name": "Dark",
        "perceived_colour_master_id": "5",
        "perceived_colour_master_name": "Black",
        "department_no": "1939",
        "department_name": "Woven bottoms",
        "index_code": "A",
        "index_name": "Ladieswear",
        "index_group_no": "1",
        "index_group_name": "Ladieswear",
        "section_no": "2",
        "section_name": "H&M+",
        "garment_group_no": "1009",
        "garment_group_name": "Trousers",
        "detail_desc": "Pull-on trousers in an airy viscose weave with wide elastication and a drawstring at the waist. Relaxed fit with side pockets and tapered legs."
    }
]