[
    {
        "article_id": "0660757001",
        "product_code": "0660757",
        "prod_name": "SPD YALE hood",
        "product_type_no": "308",
        "product_type_name": "Hoodie",
        "product_group_name": "Garment Upper body",
        "graphical_appearance_no": "1010010",
        "graphical_appearance_name": "Melange",
        "colour_group_code": "73",
        "colour_group_name": "Dark Blue",
        "perceived_colour_value_id": "4",
        "perceived_colour_value_name": "Dark",
        "perceived_colour_master_id": "2",
        "perceived_colour_master_name": "Blue",
        "department_no": "7648",
        "department_name": "Kids Boy Jersey Fancy",
        "index_code": "H",
        "index_name": "Children Sizes 92-140",
        "index_group_no": "4",
        "index_group_name": "Baby/Children",
        "section_no": "46",
        "section_name": "Kids Boy",
        "garment_group_no": "1005",
        "garment_group_name": "Jersey Fancy",
        "detail_desc": "Block-coloured top in printed sweatshirt fabric with a hood, kangaroo pocket and ribbing at the cuffs and hem. Soft brushed inside."
    },
    {
        "article_id": "0660758001",
        "product_code": "0660758",
        "prod_name": "SPD DARTMOUTH shorts",
        "product_type_no": "274",
        "product_type_name": "Shorts",
        "product_group_name": "Garment Lower body",
        "graphical_appearance_no": "1010010",
        "graphical_appearance_name": "Melange",
        "colour_group_code": "73",
        "colour_group_name": "Dark Blue",
        "perceived_colour_value_id": "4",
        "perceived_colour_value_name": "Dark",
        "perceived_colour_master_id": "2",
        "perceived_colour_master_name": "Blue",
        "department_no": "7648",
        "department_name": "Kids Boy Jersey Fancy",
        "index_code": "H",
        "index_name": "Children Sizes 92-140",
        "index_group_no": "4",
        "index_group_name": "Baby/Children",
        "section_no": "46",
        "section_name": "Kids Boy",
        "garment_group_no": "1005",
        "garment_group_name": "Jersey Fancy",
        "detail_desc": "Knee-length shorts in sweatshirt fabric with a print on one leg, elasticated drawstring waist and a back pocket."
    },
    {
        "article_id": "0660759001",
        "product_code": "0660759",
        "prod_name": "SPD HARVARD hood",
        "product_type_no": "308",
        "product_type_name": "Hoodie",
        "product_group_name": "Garment Upper body",
        "graphical_appearance_no": "1010016",
        "graphical_appearance_name": "Solid",
        "colour_group_code": "73",
        "colour_group_name": "Dark Blue",
        "perceived_colour_value_id": "4",
        "perceived_colour_value_name": "Dark",
        "perceived_colour_master_id": "2",
        "perceived_colour_master_name": "Blue",
        "department_no": "7648",
        "department_name": "Kids Boy Jersey Fancy",
        "index_code": "H",
        "index_name": "Children Sizes 92-140",
        "index_group_no": "4",
        "index_group_name": "Baby/Children",
        "section_no": "46",
        "section_name": "Kids Boy",
        "garment_group_no": "1005",
        "garment_group_name": "Jersey Fancy",
        "detail_desc": "Jacket in sweatshirt fabric with appliqu\u00e9s and side stripes. Double-layered hood with a decorative drawstring, zip down the front and striped ribbing at the cuffs and hem."
    },
    {
        "article_id": "0660760001",
        "product_code": "0660760",
        "prod_name": "SPD CORNELL joggers",
        "product_type_no": "272",
        "product_type_name": "Trousers",
        "product_group_name": "Garment Lower body",
        "graphical_appearance_no": "1010016",
        "graphical_appearance_name": "Solid",
        "colour_group_code": "73",
        "colour_group_name": "Dark Blue",
        "perceived_colour_value_id": "4",
        "perceived_colour_value_name": "Dark",
        "perceived_colour_master_id": "2",
        "perceived_colour_master_name": "Blue",
        "department_no": "7648",
        "department_name": "Kids Boy Jersey Fancy",
        "index_code": "H",
        "index_name": "Children Sizes 92-140",
        "index_group_no": "4",
        "index_group_name": "Baby/Children",
        "section_no": "46",
        "section_name": "Kids Boy",
        "garment_group_no": "1005",
        "garment_group_name": "Jersey Fancy",
        "detail_desc": "Joggers in soft sweatshirt fabric with an elasticated drawstring waist, appliqu\u00e9 on one leg, side pockets and a back pocket. Legs with contrasting colour stripes down the sides and ribbed hems."
    },
    {
        "article_id": "0660761001",
        "product_code": "0660761",
        "prod_name": "SPD COLUMBIA polo",
        "product_type_no": "257",
        "product_type_name": "Polo shirt",
        "product_group_name": "Garment Upper body",
        "graphical_appearance_no": "1010005",
        "graphical_appearance_name": "Colour blocking",
        "colour_group_code": "42",
        "colour_group_name": "Red",
        "perceived_colour_value_id": "5",
        "perceived_colour_value_name": "Bright",
        "perceived_colour_master_id": "18",
        "perceived_colour_master_name": "Red",
        "department_no": "7648",
        "department_name": "Kids Boy Jersey Fancy",
        "index_code": "H",
        "index_name": "Children Sizes 92-140",
        "index_group_no": "4",
        "index_group_name": "Baby/Children",
        "section_no": "46",
        "section_name": "Kids Boy",
        "garment_group_no": "1005",
        "garment_group_name": "Jersey Fancy",
        "detail_desc": "Polo shirt in piqu\u00e9 made from a cotton blend with an appliqu\u00e9 and print motif on the chest. Ribbed collar, button placket, short sleeves in a contrasting colour with striped ribbed trims, and short slits in the sides. Slightly longer at the back."
    },
    {
        "article_id": "0660761002",
        "product_code": "0660761",
        "prod_name": "SPD COLUMBIA polo",
        "product_type_no": "257",
        "product_type_name": "Polo shirt",
        "product_group_name": "Garment Upper body",
        "graphical_appearance_no": "1010005",
        "graphical_appearance_name": "Colour blocking",
        "colour_group_code": "07",
        "colour_group_name": "Grey",
        "perceived_colour_value_id": "1",
        "perceived_colour_value_name": "Dusty Light",
        "perceived_colour_master_id": "12",
        "perceived_colour_master_name": "Grey",
        "department_no": "7648",
        "department_name": "Kids Boy Jersey Fancy",
        "index_code": "H",
        "index_name": "Children Sizes 92-140",
        "index_group_no": "4",
        "index_group_name": "Baby/Children",
        "section_no": "46",
        "section_name": "Kids Boy",
        "garment_group_no": "1005",
        "garment_group_name": "Jersey Fancy",
        "detail_desc": "Polo shirt in piqu\u00e9 made from a cotton blend with an appliqu\u00e9 and print motif on the chest. Ribbed collar, button placket, short sleeves in a contrasting colour with striped ribbed trims, and short slits in the sides. Slightly longer at the back."
    },
    {
        "article_id": "0660791001",
        "product_code": "0660791",
        "prod_name": "Flare H.W",
        "product_type_no": "272",
        "product_type_name": "Trousers",
        "product_group_name": "Garment Lower body",
        "graphical_appearance_no": "1010023",
        "graphical_appearance_name": "Denim",
        "colour_group_code": "72",
        "colour_group_name": "Blue",
        "perceived_colour_value_id": "2",
        "perceived_colour_value_name": "Medium Dusty",
        "perceived_colour_master_id": "2",
        "perceived_colour_master_name": "Blue",
        "department_no": "1772",
        "department_name": "Denim Trousers",
        "index_code": "D",
        "index_name": "Divided",
        "index_group_no": "2",
        "index_group_name": "Divided",
        "section_no": "57",
        "section_name": "Ladies Denim",
        "garment_group_no": "1016",
        "garment_group_name": "Trousers Denim",
        "detail_desc": "5-pocket jeans in washed stretch denim with worn details, a high waist, zip fly and button and flared legs."
    },
    {
        "article_id": "0660795001",
        "product_code": "0660795",
        "prod_name": "Kira top",
        "product_type_no": "253",
        "product_type_name": "Vest top",
        "product_group_name": "Garment Upper body",
        "graphical_appearance_no": "1010016",
        "graphical_appearance_name": "Solid",
        "colour_group_code": "33",
        "colour_group_name": "Dark Orange",
        "perceived_colour_value_id": "5",
        "perceived_colour_value_name": "Bright",
        "perceived_colour_master_id": "3",
        "perceived_colour_master_name": "Orange",
        "department_no": "1636",
        "department_name": "Jersey fancy",
        "index_code": "A",
        "index_name": "Ladieswear",
        "index_group_no": "1",
        "index_group_name": "Ladieswear",
        "section_no": "15",
        "section_name": "Womens Everyday Collection",
        "garment_group_no": "1005",
        "garment_group_name": "Jersey Fancy",
        "detail_desc": "Short, sleeveless top in viscose jersey with a deep, rib-trimmed neckline, ribbing around the armholes and an overlocked hem with ties at the front."
    },
    {
        "article_id": "0660795002",
        "product_code": "0660795",
        "prod_name": "Kira top",
        "product_type_no": "253",
        "product_type_name": "Vest top",
        "product_group_name": "Garment Upper body",
        "graphical_appearance_no": "1010016",
        "graphical_appearance_name": "Solid",
        "colour_group_code": "71",
        "colour_group_name": "Light Blue",
        "perceived_colour_value_id": "1",
        "perceived_colour_value_name": "Dusty Light",
        "perceived_colour_master_id": "2",
        "perceived_colour_master_name": "Blue",
        "department_no": "1636",
        "department_name": "Jersey fancy",
        "index_code": "A",
        "index_name": "Ladieswear",
        "index_group_no": "1",
        "index_group_name": "Ladieswear",
        "section_no": "15",
        "section_name": "Womens Everyday Collection",
        "garment_group_no": "1005",
        "garment_group_name": "Jersey Fancy",
        "detail_desc": "Short, sleeveless top in viscose jersey with a deep, rib-trimmed neckline, ribbing around the armholes and an overlocked hem with ties at the front."
    },
    {
        "article_id": "0660795003",
        "product_code": "0660795",
        "prod_name": "Kira top",
        "product_type_no": "253",
        "product_type_name": "Vest top",
        "product_group_name": "Garment Upper body",
        "graphical_appearance_no": "1010016",
        "graphical_appearance_name": "Solid",
        "colour_group_code": "09",
        "colour_group_name": "Black",
        "perceived_colour_value_id": "4",
        "perceived_colour_value_name": "Dark",
        "perceived_colour_master_id": "5",
        "perceived_colour_master_name": "Black",
        "department_no": "1636",
        "department_name": "Jersey fancy",
        "index_code": "A",
        "index_name": "Ladieswear",
        "index_group_no": "1",
        "index_group_name": "Ladieswear",
        "section_no": "15",
        "section_name": "Womens Everyday Collection",
        "garment_group_no": "1005",
        "garment_group_name": "Jersey Fancy",
        "detail_desc": "Short, sleeveless top in viscose jersey with a deep, rib-trimmed neckline, ribbing around the armholes and an overlocked hem with ties at the front."
    },
    {
        "article_id": "0660795004",
        "product_code": "0660795",
        "prod_name": "Kira top",
        "product_type_no": "253",
        "product_type_name": "Vest top",
        "product_group_name": "Garment Upper body",
        "graphical_appearance_no": "1010016",
        "graphical_appearance_name": "Solid",
        "colour_group_code": "10",
        "colour_group_name": "White",
        "perceived_colour_value_id": "3",
        "perceived_colour_value_name": "Light",
        "perceived_colour_master_id": "9",
        "perceived_colour_master_name": "White",
        "department_no": "1636",
        "department_name": "Jersey fancy",
        "index_code": "A",
        "index_name": "Ladieswear",
        "index_group_no": "1",
        "index_group_name": "Ladieswear",
        "section_no": "15",
        "section_name": "Womens Everyday Collection",
        "garment_group_no": "1005",
        "garment_group_name": "Jersey Fancy",
        "detail_desc": "Short, sleeveless top in viscose jersey with a deep, rib-trimmed neckline, ribbing around the armholes and an overlocked hem with ties at the front."
    },
    {
        "article_id": "0660821001",
        "product_code": "0660821",
        "prod_name": "Elsa canvas cross",
        "product_type_no": "66",
        "product_type_name": "Bag",
        "product_group_name": "Accessories",
        "graphical_appearance_no": "1010016",
        "graphical_appearance_name": "Solid",
        "colour_group_code": "10",
        "colour_group_name": "White",
        "perceived_colour_value_id": "3",
        "perceived_colour_value_name": "Light",
        "perceived_colour_master_id": "9",
        "perceived_colour_master_name": "White",
        "department_no": "1920",
        "department_name": "Small Bags",
        "index_code": "C",
        "index_name": "Ladies Accessories",
        "index_group_no": "1",
        "index_group_name": "Ladieswear",
        "section_no": "65",
        "section_name": "Womens Big accessories",
        "garment_group_no": "1019",
        "garment_group_name": "Accessories",
        "detail_desc": "Small shoulder bag in canvas with suede details, a narrow metal chain shoulder strap and a flap with a magnetic fastener. Card compartment inside with space for three cards. Lined. Size 7.5x17x21 cm."
    },
    {
        "article_id": "0660830001",
        "product_code": "0660830",
        "prod_name": "Fine knit heaven",
        "product_type_no": "252",
        "product_type_name": "Sweater",
        "product_group_name": "Garment Upper body",
        "graphical_appearance_no": "1010016",
        "graphical_appearance_name": "Solid",
        "colour_group_code": "09",
        "colour_group_name": "Black",
        "perceived_colour_value_id": "4",
        "perceived_colour_value_name": "Dark",
        "perceived_colour_master_id": "5",
        "perceived_colour_master_name": "Black",
        "department_no": "1626",
        "department_name": "Knitwear",
        "index_code": "A",
        "index_name": "Ladieswear",
        "index_group_no": "1",
        "index_group_name": "Ladieswear",
        "section_no": "15",
        "section_name": "Womens Everyday Collection",
        "garment_group_no": "1003",
        "garment_group_name": "Knitwear",
        "detail_desc": "Jumper in a soft, fine-knit viscose blend with a decorative seam front and back, dropped shoulders and long sleeves. Ribbing around the neckline, cuffs and hem and short slits in the sides. Longer at the back."
    },
    {
        "article_id": "0660830002",
        "product_code": "0660830",
        "prod_name": "Fine knit heaven",
        "product_type_no": "252",
        "product_type_name": "Sweater",
        "product_group_name": "Garment Upper body",
        "graphical_appearance_no": "1010010",
        "graphical_appearance_name": "Melange",
        "colour_group_code": "73",
        "colour_group_name": "Dark Blue",
        "perceived_colour_value_id": "2",
        "perceived_colour_value_name": "Medium Dusty",
        "perceived_colour_master_id": "2",
        "perceived_colour_master_name": "Blue",
        "department_no": "1626",
        "department_name": "Knitwear",
        "index_code": "A",
        "index_name": "Ladieswear",
        "index_group_no": "1",
        "index_group_name": "Ladieswear",
        "section_no": "15",
        "section_name": "Womens Everyday Collection",
        "garment_group_no": "1003",
        "garment_group_name": "Knitwear",
        "detail_desc": "Jumper in a soft, fine-knit viscose blend with a decorative seam front and back, dropped shoulders and long sleeves. Ribbing around the neckline, cuffs and hem and short slits in the sides. Longer at the back."
    },
    {
        "article_id": "0660830003",
        "product_code": "0660830",
        "prod_name": "Fine knit heaven",
        "product_type_no": "252",
        "product_type_name": "Sweater",
        "product_group_name": "Garment Upper body",
        "graphical_appearance_no": "1010010",
        "graphical_appearance_name": "Melange",
        "colour_group_code": "43",
        "colour_group_name": "Dark Red",
        "perceived_colour_value_id": "4",
        "perceived_colour_value_name": "Dark",
        "perceived_colour_master_id": "18",
        "perceived_colour_master_name": "Red",
        "department_no": "1626",
        "department_name": "Knitwear",
        "index_code": "A",
        "index_name": "Ladieswear",
        "index_group_no": "1",
        "index_group_name": "Ladieswear",
        "section_no": "15",
        "section_name": "Womens Everyday Collection",
        "garment_group_no": "1003",
        "garment_group_name": "Knitwear",
        "detail_desc": "Jumper in a soft, fine-knit viscose blend with a decorative seam front and back, dropped shoulders and long sleeves. Ribbing around the neckline, cuffs and hem and short slits in the sides. Longer at the back."
    },
    {
        "article_id": "0660830004",
        "product_code": "0660830",
        "prod_name": "Fine knit heaven",
        "product_type_no": "252",
        "product_type_name": "Sweater",
        "product_group_name": "Garment Upper body",
        "graphical_appearance_no": "1010010",
        "graphical_appearance_name": "Melange",
        "colour_group_code": "12",
        "colour_group_name": "Light Beige",
        "perceived_colour_value_id": "1",
        "perceived_colour_value_name": "Dusty Light",
        "perceived_colour_master_id": "11",
        "perceived_colour_master_name": "Beige",
        "department_no": "1626",
        "department_name": "Knitwear",
        "index_code": "A",
        "index_name": "Ladieswear",
        "index_group_no": "1",
        "index_group_name": "Ladieswear",
        "section_no": "15",
        "section_name": "Womens Everyday Collection",
        "garment_group_no": "1003",
        "garment_group_name": "Knitwear",
        "detail_desc": "Jumper in a soft, fine-knit viscose blend with a decorative seam front and back, dropped shoulders and long sleeves. Ribbing around the neckline, cuffs and hem and short slits in the sides. Longer at the back."
    },
    {
        "article_id": "0660830005",
        "product_code": "0660830",
        "prod_name": "Fine knit heaven",
        "product_type_no": "252",
        "product_type_name": "Sweater",
        "product_group_name": "Garment Upper body",
        "graphical_appearance_no": "1010010",
        "graphical_appearance_name": "Melange",
        "colour_group_code": "33",
        "colour_group_name": "Dark Orange",
        "perceived_colour_value_id": "4",
        "perceived_colour_value_name": "Dark",
        "perceived_colour_master_id": "3",
        "perceived_colour_master_name": "Orange",
        "department_no": "1626",
        "department_name": "Knitwear",
        "index_code": "A",
        "index_name": "Ladieswear",
        "index_group_no": "1",
        "index_group_name": "Ladieswear",
        "section_no": "15",
        "section_name": "Womens Everyday Collection",
        "garment_group_no": "1003",
        "garment_group_name": "Knitwear",
        "detail_desc": "Jumper in a soft, fine-knit viscose blend with a decorative seam front and back, dropped shoulders and long sleeves. Ribbing around the neckline, cuffs and hem and short slits in the sides. Longer at the back."
    },
    {
        "article_id": "0660830006",
        "product_code": "0660830",
        "prod_name": "Fine knit heaven",
        "product_type_no": "252",
        "product_type_name": "Sweater",
        "product_group_name": "Garment Upper body",
        "graphical_appearance_no": "1010010",
        "graphical_appearance_name": "Melange",
        "colour_group_code": "93",
        "colour_group_name": "Dark Green",
        "perceived_colour_value_id": "7",
        "perceived_colour_value_name": "Medium",
        "perceived_colour_master_id": "19",
        "perceived_colour_master_name": "Green",
        "department_no": "1626",
        "department_name": "Knitwear",
        "index_code": "A",
        "index_name": "Ladieswear",
        "index_group_no": "1",
        "index_group_name": "Ladieswear",
        "section_no": "15",
        "section_name": "Womens Everyday Collection",
        "garment_group_no": "1003",
        "garment_group_name": "Knitwear",
        "detail_desc": "Jumper in a soft, fine-knit viscose blend with a decorative seam front and back, dropped shoulders and long sleeves. Ribbing around the neckline, cuffs and hem and short slits in the sides. Longer at the back."
    },
    {
        "article_id": "0660835001",
        "product_code": "0660835",
        "prod_name": "Milou Jumpsuit.",
        "product_type_no": "267",
        "product_type_name": "Jumpsuit/Playsuit",
        "product_group_name": "Garment Full body",
        "graphical_appearance_no": "1010016",
        "graphical_appearance_name": "Solid",
        "colour_group_code": "52",
        "colour_group_name": "Pink",
        "perceived_colour_value_id": "3",
        "perceived_colour_value_name": "Light",
        "perceived_colour_master_id": "4",
        "perceived_colour_master_name": "Pink",
        "department_no": "7616",
        "department_name": "Kids Girl Jersey Fancy",
        "index_code": "H",
        "index_name": "Children Sizes 92-140",
        "index_group_no": "4",
        "index_group_name": "Baby/Children",
        "section_no": "76",
        "section_name": "Kids Girl",
        "garment_group_no": "1005",
        "garment_group_name": "Jersey Fancy",
        "detail_desc": "Ankle-length jumpsuit in soft slub cotton jersey with lace detailing at the top, an opening with a button at the back of the neck and short flounced sleeves in woven fabric. Gathered seam at the waist, side pockets and straight legs."
    },
    {
        "article_id": "0660836001",
        "product_code": "0660836",
        "prod_name": "Doris metallic",
        "product_type_no": "86",
        "product_type_name": "Ballerinas",
        "product_group_name": "Shoes",
        "graphical_appearance_no": "1010016",
        "graphical_appearance_name": "Solid",
        "colour_group_code": "09",
        "colour_group_name": "Black",
        "perceived_colour_value_id": "4",
        "perceived_colour_value_name": "Dark",
        "perceived_colour_master_id": "5",
        "perceived_colour_master_name": "Black",
        "department_no": "6561",
        "department_name": "Baby Shoes",
        "index_code": "G",
        "index_name": "Baby Sizes 50-98",
        "index_group_no": "4",
        "index_group_name": "Baby/Children",
        "section_no": "42",
        "section_name": "Kids & Baby Shoes",
        "garment_group_no": "1020",
        "garment_group_name": "Shoes",
        "detail_desc": "Ballet pumps with a bow at the front, elastic strap over the foot and a loop at the back. Fabric linings and insoles and rubber soles."
    },
    {
        "article_id": "0660836002",
        "product_code": "0660836",
        "prod_name": "Doris metallic",
        "product_type_no": "86",
        "product_type_name": "Ballerinas",
        "product_group_name": "Shoes",
        "graphical_appearance_no": "1010011",
        "graphical_appearance_name": "Metallic",
        "colour_group_code": "31",
        "colour_group_name": "Light Orange",
        "perceived_colour_value_id": "1",
        "perceived_colour_value_name": "Dusty Light",
        "perceived_colour_master_id": "3",
        "perceived_colour_master_name": "Orange",
        "department_no": "6561",
        "department_name": "Baby Shoes",
        "index_code": "G",
        "index_name": "Baby Sizes 50-98",
        "index_group_no": "4",
        "index_group_name": "Baby/Children",
        "section_no": "42",
        "section_name": "Kids & Baby Shoes",
        "garment_group_no": "1020",
        "garment_group_name": "Shoes",
        "detail_desc": "Ballet pumps with a bow at the front, elastic strap over the foot and a loop at the back. Fabric linings and insoles and rubber soles."
    },
    {
        "article_id": "0660851001",
        "product_code": "0660851",
        "prod_name": "Daniel flowerprinted trs",
        "product_type_no": "272",
        "product_type_name": "Trousers",
        "product_group_name": "Garment Lower body",
        "graphical_appearance_no": "1010001",
        "graphical_appearance_name": "All over pattern",
        "colour_group_code": "09",
        "colour_group_name": "Black",
        "perceived_colour_value_id": "4",
        "perceived_colour_value_name": "Dark",
        "perceived_colour_master_id": "5",
        "perceived_colour_master_name": "Black",
        "department_no": "5641",
        "department_name": "Local relevance",
        "index_code": "F",
        "index_name": "Menswear",
        "index_group_no": "3",
        "index_group_name": "Menswear",
        "section_no": "24",
        "section_name": "Men Project",
        "garment_group_no": "1001",
        "garment_group_name": "Unknown",
        "detail_desc": "Suit trousers in a patterned weave with a regular waist, concealed fastening and zip fly. Side pockets, welt back pockets and tapered legs with turn-ups at the hems."
    },
    {
        "article_id": "0660886001",
        "product_code": "0660886",
        "prod_name": "H-set basic box",
        "product_type_no": "78",
        "product_type_name": "Other accessories",
        "product_group_name": "Accessories",
        "graphical_appearance_no": "1010016",
        "graphical_appearance_name": "Solid",
        "colour_group_code": "51",
        "colour_group_name": "Light Pink",
        "perceived_colour_value_id": "3",
        "perceived_colour_value_name": "Light",
        "perceived_colour_master_id": "4",
        "perceived_colour_master_name": "Pink",
        "department_no": "4313",
        "department_name": "Girls Small Acc/Bags",
        "index_code": "J",
        "index_name": "Children Accessories, Swimwear",
        "index_group_no": "4",
        "index_group_name": "Baby/Children",
        "section_no": "43",
        "section_name": "Kids Accessories, Swimwear & D",
        "garment_group_no": "1019",
        "garment_group_name": "Accessories",
        "detail_desc": "Heart-shaped plastic pot with an eyelet and satin ribbon at the top. Contains plastic hair clips and hair elastics. Size approx. 2.5x10.5x11.5 cm. Not for children under 3."
    },
    {
        "article_id": "0660887001",
        "product_code": "0660887",
        "prod_name": "Kimberly skirt",
        "product_type_no": "275",
        "product_type_name": "Skirt",
        "product_group_name": "Garment Lower body",
        "graphical_appearance_no": "1010001",
        "graphical_appearance_name": "All over pattern",
        "colour_group_code": "51",
        "colour_group_name": "Light Pink",
        "perceived_colour_value_id": "1",
        "perceived_colour_value_name": "Dusty Light",
        "perceived_colour_master_id": "4",
        "perceived_colour_master_name": "Pink",
        "department_no": "1444",
        "department_name": "Skirts",
        "index_code": "D",
        "index_name": "Divided",
        "index_group_no": "2",
        "index_group_name": "Divided",
        "section_no": "53",
        "section_name": "Divided Collection",
        "garment_group_no": "1012",
        "garment_group_name": "Skirts",
        "detail_desc": "Short skirt in patterned jersey cr\u00eape with an elasticated drawstring waist and a frill-trimmed seam above the hem. Unlined."
    },
    {
        "article_id": "0660900001",
        "product_code": "0660900",
        "prod_name": "Robin skirt",
        "product_type_no": "275",
        "product_type_name": "Skirt",
        "product_group_name": "Garment Lower body",
        "graphical_appearance_no": "1010016",
        "graphical_appearance_name": "Solid",
        "colour_group_code": "51",
        "colour_group_name": "Light Pink",
        "perceived_colour_value_id": "1",
        "perceived_colour_value_name": "Dusty Light",
        "perceived_colour_master_id": "4",
        "perceived_colour_master_name": "Pink",
        "department_no": "1444",
        "department_name": "Skirts",
        "index_code": "D",
        "index_name": "Divided",
        "index_group_no": "2",
        "index_group_name": "Divided",
        "section_no": "53",
        "section_name": "Divided Collection",
        "garment_group_no": "1012",
        "garment_group_name": "Skirts",
        "detail_desc": "Short skirt in a patterned weave with a sewn-in wrapover with a draped effect at the front and decorative tie at one side. Concealed zip at the back and an asymmetric hem. Unlined."
    },
    {
        "article_id": "0660920001",
        "product_code": "0660920",
        "prod_name": "Rico Minis SW.",
        "product_type_no": "59",
        "product_type_name": "Swimwear bottom",
        "product_group_name": "Swimwear",
        "graphical_appearance_no": "1010014",
        "graphical_appearance_name": "Placement print",
        "colour_group_code": "09",
        "colour_group_name": "Black",
        "perceived_colour_value_id": "4",
        "perceived_colour_value_name": "Dark",
        "perceived_colour_master_id": "5",
        "perceived_colour_master_name": "Black",
        "department_no": "1645",
        "department_name": "Divided Swimwear",
        "index_code": "D",
        "index_name": "Divided",
        "index_group_no": "2",
        "index_group_name": "Divided",
        "section_no": "51",
        "section_name": "Divided Basics",
        "garment_group_no": "1018",
        "garment_group_name": "Swimwear",
        "detail_desc": "Fully lined bikini bottoms with a text print at the back and ties at the sides."
    },
    {
        "article_id": "0660921001",
        "product_code": "0660921",
        "prod_name": "Barbados Briefs SW.",
        "product_type_no": "59",
        "product_type_name": "Swimwear bottom",
        "product_group_name": "Swimwear",
        "graphical_appearance_no": "1010001",
        "graphical_appearance_name": "All over pattern",
        "colour_group_code": "52",
        "colour_group_name": "Pink",
        "perceived_colour_value_id": "7",
        "perceived_colour_value_name": "Medium",
        "perceived_colour_master_id": "4",
        "perceived_colour_master_name": "Pink",
        "department_no": "1645",
        "department_name": "Divided Swimwear",
        "index_code": "D",
        "index_name": "Divided",
        "index_group_no": "2",
        "index_group_name": "Divided",
        "section_no": "51",
        "section_name": "Divided Basics",
        "garment_group_no": "1018",
        "garment_group_name": "Swimwear",
        "detail_desc": "Fully lined, patterned bikini bottoms."
    },
    {
        "article_id": "0660924001",
        "product_code": "0660924",
        "prod_name": "Cayman High Briefs SW.",
        "product_type_no": "59",
        "product_type_name": "Swimwear bottom",
        "product_group_name": "Swimwear",
        "graphical_appearance_no": "1010001",
        "graphical_appearance_name": "All over pattern",
        "colour_group_code": "93",
        "colour_group_name": "Dark Green",
        "perceived_colour_value_id": "4",
        "perceived_colour_value_name": "Dark",
        "perceived_colour_master_id": "19",
        "perceived_colour_master_name": "Green",
        "department_no": "1645",
        "department_name": "Divided Swimwear",
        "index_code": "D",
        "index_name": "Divided",
        "index_group_no": "2",
        "index_group_name": "Divided",
        "section_no": "51",
        "section_name": "Divided Basics",
        "garment_group_no": "1018",
        "garment_group_name": "Swimwear",
        "detail_desc": "Fully lined, high-waisted, patterned bikini bottoms with an elastic waistband."
    },
    {
        "article_id": "0660927001",
        "product_code": "0660927",
        "prod_name": "Libre Bottoms SW.",
        "product_type_no": "59",
        "product_type_name": "Swimwear bottom",
        "product_group_name": "Swimwear",
        "graphical_appearance_no": "1010016",
        "graphical_appearance_name": "Solid",
        "colour_group_code": "22",
        "colour_group_name": "Yellow",
        "perceived_colour_value_id": "5",
        "perceived_colour_value_name": "Bright",
        "perceived_colour_master_id": "8",
        "perceived_colour_master_name": "Yellow",
        "department_no": "1645",
        "department_name": "Divided Swimwear",
        "index_code": "D",
        "index_name": "Divided",
        "index_group_no": "2",
        "index_group_name": "Divided",
        "section_no": "51",
        "section_name": "Divided Basics",
        "garment_group_no": "1018",
        "garment_group_name": "Swimwear",
        "detail_desc": "Fully lined bikini bottoms with a high cut at the back."
    },
    {
        "article_id": "0660927002",
        "product_code": "0660927",
        "prod_name": "Libre Bottoms SW.",
        "product_type_no": "59",
        "product_type_name": "Swimwear bottom",
        "product_group_name": "Swimwear",
        "graphical_appearance_no": "1010016",
        "graphical_appearance_name": "Solid",
        "colour_group_code": "42",
        "colour_group_name": "Red",
        "perceived_colour_value_id": "5",
        "perceived_colour_value_name": "Bright",
        "perceived_colour_master_id": "18",
        "perceived_colour_master_name": "Red",
        "department_no": "1645",
        "department_name": "Divided Swimwear",
        "index_code": "D",
        "index_name": "Divided",
        "index_group_no": "2",
        "index_group_name": "Divided",
        "section_no": "51",
        "section_name": "Divided Basics",
        "garment_group_no": "1018",
        "garment_group_name": "Swimwear",
        "detail_desc": "Fully lined bikini bottoms with a high cut at the back."
    },
    {
        "article_id": "0660930001",
        "product_code": "0660930",
        "prod_name": "Maui High waist SW.",
        "product_type_no": "59",
        "product_type_name": "Swimwear bottom",
        "product_group_name": "Swimwear",
        "graphical_appearance_no": "1010001",
        "graphical_appearance_name": "All over pattern",
        "colour_group_code": "22",
        "colour_group_name": "Yellow",
        "perceived_colour_value_id": "5",
        "perceived_colour_value_name": "Bright",
        "perceived_colour_master_id": "8",
        "perceived_colour_master_name": "Yellow",
        "department_no": "1645",
        "department_name": "Divided Swimwear",
        "index_code": "D",
        "index_name": "Divided",
        "index_group_no": "2",
        "index_group_name": "Divided",
        "section_no": "51",
        "section_name": "Divided Basics",
        "garment_group_no": "1018",
        "garment_group_name": "Swimwear",
        "detail_desc": "Fully lined, patterned bikini bottoms with a high waist."
    },
    {
        "article_id": "0660985003",
        "product_code": "0660985",
        "prod_name": "bally",
        "product_type_no": "252",
        "product_type_name": "Sweater",
        "product_group_name": "Garment Upper body",
        "graphical_appearance_no": "1010016",
        "graphical_appearance_name": "Solid",
        "colour_group_code": "51",
        "colour_group_name": "Light Pink",
        "perceived_colour_value_id": "3",
        "perceived_colour_value_name": "Light",
        "perceived_colour_master_id": "4",
        "perceived_colour_master_name": "Pink",
        "department_no": "5884",
        "department_name": "Knitwear",
        "index_code": "F",
        "index_name": "Menswear",
        "index_group_no": "3",
        "index_group_name": "Menswear",
        "section_no": "55",
        "section_name": "Contemporary Street",
        "garment_group_no": "1003",
        "garment_group_name": "Knitwear",
        "detail_desc": "Long-sleeved jumper in a soft knit with ribbing around the neckline, cuffs and hem."
    },
    {
        "article_id": "0660985004",
        "product_code": "0660985",
        "prod_name": "bally",
        "product_type_no": "252",
        "product_type_name": "Sweater",
        "product_group_name": "Garment Upper body",
        "graphical_appearance_no": "1010016",
        "graphical_appearance_name": "Solid",
        "colour_group_code": "09",
        "colour_group_name": "Black",
        "perceived_colour_value_id": "4",
        "perceived_colour_value_name": "Dark",
        "perceived_colour_master_id": "5",
        "perceived_colour_master_name": "Black",
        "department_no": "5884",
        "department_name": "Knitwear",
        "index_code": "F",
        "index_name": "Menswear",
        "index_group_no": "3",
        "index_group_name": "Menswear",
        "section_no": "55",
        "section_name": "Contemporary Street",
        "garment_group_no": "1003",
        "garment_group_name": "Knitwear",
        "detail_desc": "Long-sleeved jumper in a soft knit with ribbing around the neckline, cuffs and hem."
    },
    {
        "article_id": "0660985005",
        "product_code": "0660985",
        "prod_name": "bally",
        "product_type_no": "252",
        "product_type_name": "Sweater",
        "product_group_name": "Garment Upper body",
        "graphical_appearance_no": "1010016",
        "graphical_appearance_name": "Solid",
        "colour_group_code": "10",
        "colour_group_name": "White",
        "perceived_colour_value_id": "3",
        "perceived_colour_value_name": "Light",
        "perceived_colour_master_id": "9",
        "perceived_colour_master_name": "White",
        "department_no": "5884",
        "department_name": "Knitwear",
        "index_code": "F",
        "index_name": "Menswear",
        "index_group_no": "3",
        "index_group_name": "Menswear",
        "section_no": "55",
        "section_name": "Contemporary Street",
        "garment_group_no": "1003",
        "garment_group_name": "Knitwear",
        "detail_desc": "Long-sleeved jumper in a soft knit with ribbing around the neckline, cuffs and hem."
    },
    {
        "article_id": "0660988001",
        "product_code": "0660988",
        "prod_name": "Pooka Summer Campaign dress",
        "product_type_no": "265",
        "product_type_name": "Dress",
        "product_group_name": "Garment Full body",
        "graphical_appearance_no": "1010001",
        "graphical_appearance_name": "All over pattern",
        "colour_group_code": "10",
        "colour_group_name": "White",
        "perceived_colour_value_id": "3",
        "perceived_colour_value_name": "Light",
        "perceived_colour_master_id": "9",
        "perceived_colour_master_name": "White",
        "department_no": "3090",
        "department_name": "Campaigns",
        "index_code": "A",
        "index_name": "Ladieswear",
        "index_group_no": "1",
        "index_group_name": "Ladieswear",
        "section_no": "15",
        "section_name": "Womens Everyday Collection",
        "garment_group_no": "1023",
        "garment_group_name": "Special Offers",
        "detail_desc": "Calf-length dress in a patterned cotton weave with a smocked bodice, seam at the waist and flared skirt with flounces. Lined with a short skirt."
    },
    {
        "article_id": "0660991001",
        "product_code": "0660991",
        "prod_name": "Belmont Summer Campaign dress",
        "product_type_no": "265",
        "product_type_name": "Dress",
        "product_group_name": "Garment Full body",
        "graphical_appearance_no": "1010001",
        "graphical_appearance_name": "All over pattern",
        "colour_group_code": "71",
        "colour_group_name": "Light Blue",
        "perceived_colour_value_id": "1",
        "perceived_colour_value_name": "Dusty Light",
        "perceived_colour_master_id": "2",
        "perceived_colour_master_name": "Blue",
        "department_no": "3090",
        "department_name": "Campaigns",
        "index_code": "A",
        "index_name": "Ladieswear",
        "index_group_no": "1",
        "index_group_name": "Ladieswear",
        "section_no": "15",
        "section_name": "Womens Everyday Collection",
        "garment_group_no": "1023",
        "garment_group_name": "Special Offers",
        "detail_desc": "Sleeveless dress in a plumeti cotton weave with narrow shoulder straps that cross at the back. Concealed zip in one side, a seam under the bust with pleats and a wide skirt. Lined."
    },
    {
        "article_id": "0660994002",
        "product_code": "0660994",
        "prod_name": "Rosalie tulle skirt",
        "product_type_no": "275",
        "product_type_name": "Skirt",
        "product_group_name": "Garment Lower body",
        "graphical_appearance_no": "1010016",
        "graphical_appearance_name": "Solid",
        "colour_group_code": "51",
        "colour_group_name": "Light Pink",
        "perceived_colour_value_id": "1",
        "perceived_colour_value_name": "Dusty Light",
        "perceived_colour_master_id": "4",
        "perceived_colour_master_name": "Pink",
        "department_no": "7613",
        "department_name": "Kids Girl Dresses",
        "index_code": "H",
        "index_name": "Children Sizes 92-140",
        "index_group_no": "4",
        "index_group_name": "Baby/Children",
        "section_no": "76",
        "section_name": "Kids Girl",
        "garment_group_no": "1014",
        "garment_group_name": "Dresses/Skirts girls",
        "detail_desc": "Skirt in tulle with glitter. Elastic waistband with a bow, seam with a small frill trim and a flounced tier to the hem. Lined."
    },
    {
        "article_id": "0660994003",
        "product_code": "0660994",
        "prod_name": "Rosalie tulle skirt",
        "product_type_no": "275",
        "product_type_name": "Skirt",
        "product_group_name": "Garment Lower body",
        "graphical_appearance_no": "1010016",
        "graphical_appearance_name": "Solid",
        "colour_group_code": "42",
        "colour_group_name": "Red",
        "perceived_colour_value_id": "7",
        "perceived_colour_value_name": "Medium",
        "perceived_colour_master_id": "18",
        "perceived_colour_master_name": "Red",
        "department_no": "7613",
        "department_name": "Kids Girl Dresses",
        "index_code": "H",
        "index_name": "Children Sizes 92-140",
        "index_group_no": "4",
        "index_group_name": "Baby/Children",
        "section_no": "76",
        "section_name": "Kids Girl",
        "garment_group_no": "1014",
        "garment_group_name": "Dresses/Skirts girls",
        "detail_desc": "Skirt in tulle with glitter. Elastic waistband with a bow, seam with a small frill trim and a flounced tier to the hem. Lined."
    },
    {
        "article_id": "0660994004",
        "product_code": "0660994",
        "prod_name": "Rosalie tulle skirt",
        "product_type_no": "275",
        "product_type_name": "Skirt",
        "product_group_name": "Garment Lower body",
        "graphical_appearance_no": "1010016",
        "graphical_appearance_name": "Solid",
        "colour_group_code": "73",
        "colour_group_name": "Dark Blue",
        "perceived_colour_value_id": "4",
        "perceived_colour_value_name": "Dark",
        "perceived_colour_master_id": "2",
        "perceived_colour_master_name": "Blue",
        "department_no": "7613",
        "department_name": "Kids Girl Dresses",
        "index_code": "H",
        "index_name": "Children Sizes 92-140",
        "index_group_no": "4",
        "index_group_name": "Baby/Children",
        "section_no": "76",
        "section_name": "Kids Girl",
        "garment_group_no": "1014",
        "garment_group_name": "Dresses/Skirts girls",
        "detail_desc": "Skirt in tulle with glitter. Elastic waistband with a bow, seam with a small frill trim and a flounced tier to the hem. Lined."
    },
    {
        "article_id": "0660995001",
        "product_code": "0660995",
        "prod_name": "Rose body",
        "product_type_no": "253",
        "product_type_name": "Vest top",
        "product_group_name": "Garment Upper body",
        "graphical_appearance_no": "1010016",
        "graphical_appearance_name": "Solid",
        "colour_group_code": "10",
        "colour_group_name": "White",
        "perceived_colour_value_id": "3",
        "perceived_colour_value_name": "Light",
        "perceived_colour_master_id": "9",
        "perceived_colour_master_name": "White",
        "department_no": "1640",
        "department_name": "Tops Fancy Jersey",
        "index_code": "D",
        "index_name": "Divided",
        "index_group_no": "2",
        "index_group_name": "Divided",
        "section_no": "53",
        "section_name": "Divided Collection",
        "garment_group_no": "1005",
        "garment_group_name": "Jersey Fancy",
        "detail_desc": "V-neck body in lace and mesh with lined cups, narrow adjustable shoulder straps that cross at the back and press-studs at the crotch."
    },
    {
        "article_id": "0661007001",
        "product_code": "0661007",
        "prod_name": "Iris cashmere beanie",
        "product_type_no": "75",
        "product_type_name": "Hat/beanie",
        "product_group_name": "Accessories",
        "graphical_appearance_no": "1010010",
        "graphical_appearance_name": "Melange",
        "colour_group_code": "07",
        "colour_group_name": "Grey",
        "perceived_colour_value_id": "2",
        "perceived_colour_value_name": "Medium Dusty",
        "perceived_colour_master_id": "12",
        "perceived_colour_master_name": "Grey",
        "department_no": "3519",
        "department_name": "Gloves/Hats",
        "index_code": "C",
        "index_name": "Ladies Accessories",
        "index_group_no": "1",
        "index_group_name": "Ladieswear",
        "section_no": "65",
        "section_name": "Womens Big accessories",
        "garment_group_no": "1019",
        "garment_group_name": "Accessories",
        "detail_desc": "Hat knitted in soft cashmere."
    },
    {
        "article_id": "0661007002",
        "product_code": "0661007",
        "prod_name": "Iris cashmere beanie",
        "product_type_no": "75",
        "product_type_name": "Hat/beanie",
        "product_group_name": "Accessories",
        "graphical_appearance_no": "1010016",
        "graphical_appearance_name": "Solid",
        "colour_group_code": "22",
        "colour_group_name": "Yellow",
        "perceived_colour_value_id": "7",
        "perceived_colour_value_name": "Medium",
        "perceived_colour_master_id": "8",
        "perceived_colour_master_name": "Yellow",
        "department_no": "3519",
        "department_name": "Gloves/Hats",
        "index_code": "C",
        "index_name": "Ladies Accessories",
        "index_group_no": "1",
        "index_group_name": "Ladieswear",
        "section_no": "65",
        "section_name": "Womens Big accessories",
        "garment_group_no": "1019",
        "garment_group_name": "Accessories",
        "detail_desc": "Hat knitted in soft cashmere."
    },
    {
        "article_id": "0661023001",
        "product_code": "0661023",
        "prod_name": "Flirty Mysan ring pk",
        "product_type_no": "79",
        "product_type_name": "Ring",
        "product_group_name": "Accessories",
        "graphical_appearance_no": "1010016",
        "graphical_appearance_name": "Solid",
        "colour_group_code": "51",
        "colour_group_name": "Light Pink",
        "perceived_colour_value_id": "1",
        "perceived_colour_value_name": "Dusty Light",
        "perceived_colour_master_id": "4",
        "perceived_colour_master_name": "Pink",
        "department_no": "4344",
        "department_name": "Jewellery",
        "index_code": "C",
        "index_name": "Ladies Accessories",
        "index_group_no": "1",
        "index_group_name": "Ladieswear",
        "section_no": "66",
        "section_name": "Womens Small accessories",
        "garment_group_no": "1019",
        "garment_group_name": "Accessories",
        "detail_desc": "Metal rings in various designs."
    },
    {
        "article_id": "0661023002",
        "product_code": "0661023",
        "prod_name": "Flirty Mysan ring pk.",
        "product_type_no": "79",
        "product_type_name": "Ring",
        "product_group_name": "Accessories",
        "graphical_appearance_no": "1010016",
        "graphical_appearance_name": "Solid",
        "colour_group_code": "09",
        "colour_group_name": "Black",
        "perceived_colour_value_id": "4",
        "perceived_colour_value_name": "Dark",
        "perceived_colour_master_id": "5",
        "perceived_colour_master_name": "Black",
        "department_no": "4344",
        "department_name": "Jewellery",
        "index_code": "C",
        "index_name": "Ladies Accessories",
        "index_group_no": "1",
        "index_group_name": "Ladieswear",
        "section_no": "66",
        "section_name": "Womens Small accessories",
        "garment_group_no": "1019",
        "garment_group_name": "Accessories",
        "detail_desc": "Metal rings in various designs."
    },
    {
        "article_id": "0661023003",
        "product_code": "0661023",
        "prod_name": "Flirty Mysan ring pk",
        "product_type_no": "79",
        "product_type_name": "Ring",
        "product_group_name": "Accessories",
        "graphical_appearance_no": "1010016",
        "graphical_appearance_name": "Solid",
        "colour_group_code": "93",
        "colour_group_name": "Dark Green",
        "perceived_colour_value_id": "4",
        "perceived_colour_value_name": "Dark",
        "perceived_colour_master_id": "19",
        "perceived_colour_master_name": "Green",
        "department_no": "4344",
        "department_name": "Jewellery",
        "index_code": "C",
        "index_name": "Ladies Accessories",
        "index_group_no": "1",
        "index_group_name": "Ladieswear",
        "section_no": "66",
        "section_name": "Womens Small accessories",
        "garment_group_no": "1019",
        "garment_group_name": "Accessories",
        "detail_desc": "Metal rings in various designs."
    },
    {
        "article_id": "0661023004",
        "product_code": "0661023",
        "prod_name": "Flirty Mysan ring pk.",
        "product_type_no": "79",
        "product_type_name": "Ring",
        "product_group_name": "Accessories",
        "graphical_appearance_no": "1010016",
        "graphical_appearance_name": "Solid",
        "colour_group_code": "03",
        "colour_group_name": "Silver",
        "perceived_colour_value_id": "3",
        "perceived_colour_value_name": "Light",
        "perceived_colour_master_id": "15",
        "perceived_colour_master_name": "Metal",
        "department_no": "4344",
        "department_name": "Jewellery",
        "index_code": "C",
        "index_name": "Ladies Accessories",
        "index_group_no": "1",
        "index_group_name": "Ladieswear",
        "section_no": "66",
        "section_name": "Womens Small accessories",
        "garment_group_no": "1019",
        "garment_group_name": "Accessories",
        "detail_desc": "Metal rings in various designs."
    },
    {
        "article_id": "0661023005",
        "product_code": "0661023",
        "prod_name": "Flirty Mysan ring pk.",
        "product_type_no": "79",
        "product_type_name": "Ring",
        "product_group_name": "Accessories",
        "graphical_appearance_no": "1010016",
        "graphical_appearance_name": "Solid",
        "colour_group_code": "91",
        "colour_group_name": "Light Green",
        "perceived_colour_value_id": "1",
        "perceived_colour_value_name": "Dusty Light",
        "perceived_colour_master_id": "19",
        "perceived_colour_master_name": "Green",
        "department_no": "4344",
        "department_name": "Jewellery",
        "index_code": "C",
        "index_name": "Ladies Accessories",
        "index_group_no": "1",
        "index_group_name": "Ladieswear",
        "section_no": "66",
        "section_name": "Womens Small accessories",
        "garment_group_no": "1019",
        "garment_group_name": "Accessories",
        "detail_desc": "Metal rings in various designs."
    },
    {
        "article_id": "0661023006",
        "product_code": "0661023",
        "prod_name": "Flirty Mysan ring pk.",
        "product_type_no": "79",
        "product_type_name": "Ring",
        "product_group_name": "Accessories",
        "graphical_appearance_no": "1010016",
        "graphical_appearance_name": "Solid",
        "colour_group_code": "10",
        "colour_group_name": "White",
        "perceived_colour_value_id": "3",
        "perceived_colour_value_name": "Light",
        "perceived_colour_master_id": "9",
        "perceived_colour_master_name": "White",
        "department_no": "4344",
        "department_name": "Jewellery",
        "index_code": "C",
        "index_name": "Ladies Accessories",
        "index_group_no": "1",
        "index_group_name": "Ladieswear",
        "section_no": "66",
        "section_name": "Womens Small accessories",
        "garment_group_no": "1019",
        "garment_group_name": "Accessories",
        "detail_desc": "Metal rings in various designs."
    },
    {
        "article_id": "0661023007",
        "product_code": "0661023",
        "prod_name": "Flirty Mysan ring pk.",
        "product_type_no": "79",
        "product_type_name": "Ring",
        "product_group_name": "Accessories",
        "graphical_appearance_no": "1010016",
        "graphical_appearance_name": "Solid",
        "colour_group_code": "61",
        "colour_group_name": "Light Purple",
        "perceived_colour_value_id": "3",
        "perceived_colour_value_name": "Light",
        "perceived_colour_master_id": "4",
        "perceived_colour_master_name": "Pink",
        "department_no": "4344",
        "department_name": "Jewellery",
        "index_code": "C",
        "index_name": "Ladies Accessories",
        "index_group_no": "1",
        "index_group_name": "Ladieswear",
        "section_no": "66",
        "section_name": "Womens Small accessories",
        "garment_group_no": "1019",
        "garment_group_name": "Accessories",
        "detail_desc": "Metal rings in various designs."
    },
    {
        "article_id": "0661035001",
        "product_code": "0661035",
        "prod_name": "SLIM SS",
        "product_type_no": "272",
        "product_type_name": "Trousers",
        "product_group_name": "Garment Lower body",
        "graphical_appearance_no": "1010023",
        "graphical_appearance_name": "Denim",
        "colour_group_code": "72",
        "colour_group_name": "Blue",
        "perceived_colour_value_id": "2",
        "perceived_colour_value_name": "Medium Dusty",
        "perceived_colour_master_id": "2",
        "perceived_colour_master_name": "Blue",
        "department_no": "8956",
        "department_name": "Young Boy Denim",
        "index_code": "I",
        "index_name": "Children Sizes 134-170",
        "index_group_no": "4",
        "index_group_name": "Baby/Children",
        "section_no": "47",
        "section_name": "Young Boy",
        "garment_group_no": "1016",
        "garment_group_name": "Trousers Denim",
        "detail_desc": "5-pocket slim-fit jeans in superstretch, flexible denim for maximum mobility with an adjustable, elasticated waist and zip fly. Straight cut to the hem."
    },
    {
        "article_id": "0661035006",
        "product_code": "0661035",
        "prod_name": "SLIM SS",
        "product_type_no": "272",
        "product_type_name": "Trousers",
        "product_group_name": "Garment Lower body",
        "graphical_appearance_no": "1010023",
        "graphical_appearance_name": "Denim",
        "colour_group_code": "09",
        "colour_group_name": "Black",
        "perceived_colour_value_id": "4",
        "perceived_colour_value_name": "Dark",
        "perceived_colour_master_id": "5",
        "perceived_colour_master_name": "Black",
        "department_no": "8956",
        "department_name": "Young Boy Denim",
        "index_code": "I",
        "index_name": "Children Sizes 134-170",
        "index_group_no": "4",
        "index_group_name": "Baby/Children",
        "section_no": "47",
        "section_name": "Young Boy",
        "garment_group_no": "1016",
        "garment_group_name": "Trousers Denim",
        "detail_desc": "5-pocket slim-fit jeans in superstretch, flexible denim for maximum mobility with an adjustable, elasticated waist and zip fly. Straight cut to the hem."
    },
    {
        "article_id": "0661037001",
        "product_code": "0661037",
        "prod_name": "SLIM SS",
        "product_type_no": "272",
        "product_type_name": "Trousers",
        "product_group_name": "Garment Lower body",
        "graphical_appearance_no": "1010023",
        "graphical_appearance_name": "Denim",
        "colour_group_code": "72",
        "colour_group_name": "Blue",
        "perceived_colour_value_id": "2",
        "perceived_colour_value_name": "Medium Dusty",
        "perceived_colour_master_id": "2",
        "perceived_colour_master_name": "Blue",
        "department_no": "7956",
        "department_name": "Kids Boy Denim",
        "index_code": "H",
        "index_name": "Children Sizes 92-140",
        "index_group_no": "4",
        "index_group_name": "Baby/Children",
        "section_no": "46",
        "section_name": "Kids Boy",
        "garment_group_no": "1016",
        "garment_group_name": "Trousers Denim",
        "detail_desc": "5-pocket slim-fit jeans in washed, superstretch, flexible denim for maximum mobility with an adjustable, elasticated waist, zip fly and press-stud, and straight legs."
    },
    {
        "article_id": "0661037002",
        "product_code": "0661037",
        "prod_name": "SLIM SS",
        "product_type_no": "272",
        "product_type_name": "Trousers",
        "product_group_name": "Garment Lower body",
        "graphical_appearance_no": "1010023",
        "graphical_appearance_name": "Denim",
        "colour_group_code": "73",
        "colour_group_name": "Dark Blue",
        "perceived_colour_value_id": "2",
        "perceived_colour_value_name": "Medium Dusty",
        "perceived_colour_master_id": "2",
        "perceived_colour_master_name": "Blue",
        "department_no": "7956",
        "department_name": "Kids Boy Denim",
        "index_code": "H",
        "index_name": "Children Sizes 92-140",
        "index_group_no": "4",
        "index_group_name": "Baby/Children",
        "section_no": "46",
        "section_name": "Kids Boy",
        "garment_group_no": "1016",
        "garment_group_name": "Trousers Denim",
        "detail_desc": "5-pocket slim-fit jeans in washed, superstretch, flexible denim for maximum mobility with an adjustable, elasticated waist, zip fly and press-stud, and straight legs."
    },
    {
        "article_id": "0661050002",
        "product_code": "0661050",
        "prod_name": "Marci Mid court PQ",
        "product_type_no": "94",
        "product_type_name": "Sneakers",
        "product_group_name": "Shoes",
        "graphical_appearance_no": "1010016",
        "graphical_appearance_name": "Solid",
        "colour_group_code": "17",
        "colour_group_name": "Yellowish Brown",
        "perceived_colour_value_id": "2",
        "perceived_colour_value_name": "Medium Dusty",
        "perceived_colour_master_id": "13",
        "perceived_colour_master_name": "Brown",
        "department_no": "3629",
        "department_name": "Shoes",
        "index_code": "F",
        "index_name": "Menswear",
        "index_group_no": "3",
        "index_group_name": "Menswear",
        "section_no": "27",
        "section_name": "Men Shoes",
        "garment_group_no": "1020",
        "garment_group_name": "Shoes",
        "detail_desc": "Suede trainers with a padded top edge and lacing at the front. Fabric linings and insoles and rubber soles."
    },
    {
        "article_id": "0661053001",
        "product_code": "0661053",
        "prod_name": "SKINNY BIKER",
        "product_type_no": "272",
        "product_type_name": "Trousers",
        "product_group_name": "Garment Lower body",
        "graphical_appearance_no": "1010023",
        "graphical_appearance_name": "Denim",
        "colour_group_code": "71",
        "colour_group_name": "Light Blue",
        "perceived_colour_value_id": "1",
        "perceived_colour_value_name": "Dusty Light",
        "perceived_colour_master_id": "2",
        "perceived_colour_master_name": "Blue",
        "department_no": "8956",
        "department_name": "Young Boy Denim",
        "index_code": "I",
        "index_name": "Children Sizes 134-170",
        "index_group_no": "4",
        "index_group_name": "Baby/Children",
        "section_no": "47",
        "section_name": "Young Boy",
        "garment_group_no": "1016",
        "garment_group_name": "Trousers Denim",
        "detail_desc": "5-pocket jeans in washed, stretch denim with hard-worn details, an adjustable, elasticated waist (in sizes 8-12Y), zip fly and button and slim legs with decorative seams and narrow hems."
    },
    {
        "article_id": "0661054004",
        "product_code": "0661054",
        "prod_name": "Trey Retro Runner",
        "product_type_no": "94",
        "product_type_name": "Sneakers",
        "product_group_name": "Shoes",
        "graphical_appearance_no": "1010016",
        "graphical_appearance_name": "Solid",
        "colour_group_code": "11",
        "colour_group_name": "Off White",
        "perceived_colour_value_id": "1",
        "perceived_colour_value_name": "Dusty Light",
        "perceived_colour_master_id": "9",
        "perceived_colour_master_name": "White",
        "department_no": "3629",
        "department_name": "Shoes",
        "index_code": "F",
        "index_name": "Menswear",
        "index_group_no": "3",
        "index_group_name": "Menswear",
        "section_no": "27",
        "section_name": "Men Shoes",
        "garment_group_no": "1020",
        "garment_group_name": "Shoes",
        "detail_desc": "Mesh trainers with imitation leather and imitation suede details, a padded edge and tongue, and lacing at the front. Recycled mesh linings and insoles and chunky EVA (ethylene-vinyl acetate) and rubber soles."
    },
    {
        "article_id": "0661054006",
        "product_code": "0661054",
        "prod_name": "Trey Retro Runner",
        "product_type_no": "94",
        "product_type_name": "Sneakers",
        "product_group_name": "Shoes",
        "graphical_appearance_no": "1010016",
        "graphical_appearance_name": "Solid",
        "colour_group_code": "13",
        "colour_group_name": "Beige",
        "perceived_colour_value_id": "1",
        "perceived_colour_value_name": "Dusty Light",
        "perceived_colour_master_id": "1",
        "perceived_colour_master_name": "Mole",
        "department_no": "3629",
        "department_name": "Shoes",
        "index_code": "F",
        "index_name": "Menswear",
        "index_group_no": "3",
        "index_group_name": "Menswear",
        "section_no": "27",
        "section_name": "Men Shoes",
        "garment_group_no": "1020",
        "garment_group_name": "Shoes",
        "detail_desc": "Mesh trainers with imitation leather and imitation suede details, a padded edge and tongue, and lacing at the front. Recycled mesh linings and insoles and chunky EVA (ethylene-vinyl acetate) and rubber soles."
    },
    {
        "article_id": "0661061003",
        "product_code": "0661061",
        "prod_name": "Jack Sock Runner",
        "product_type_no": "94",
        "product_type_name": "Sneakers",
        "product_group_name": "Shoes",
        "graphical_appearance_no": "1010016",
        "graphical_appearance_name": "Solid",
        "colour_group_code": "10",
        "colour_group_name": "White",
        "perceived_colour_value_id": "3",
        "perceived_colour_value_name": "Light",
        "perceived_colour_master_id": "9",
        "perceived_colour_master_name": "White",
        "department_no": "3629",
        "department_name": "Shoes",
        "index_code": "F",
        "index_name": "Menswear",
        "index_group_no": "3",
        "index_group_name": "Menswear",
        "section_no": "27",
        "section_name": "Men Shoes",
        "garment_group_no": "1020",
        "garment_group_name": "Shoes",
        "detail_desc": "Trainers in mesh with rubber details, a padded top edge, lacing at the front and a loop front and back. Mesh linings and insoles and EVA (ethylene-vinyl acetate) and rubber soles."
    },
    {
        "article_id": "0661061005",
        "product_code": "0661061",
        "prod_name": "Jack Sock Runner",
        "product_type_no": "94",
        "product_type_name": "Sneakers",
        "product_group_name": "Shoes",
        "graphical_appearance_no": "1010016",
        "graphical_appearance_name": "Solid",
        "colour_group_code": "09",
        "colour_group_name": "Black",
        "perceived_colour_value_id": "4",
        "perceived_colour_value_name": "Dark",
        "perceived_colour_master_id": "5",
        "perceived_colour_master_name": "Black",
        "department_no": "3629",
        "department_name": "Shoes",
        "index_code": "F",
        "index_name": "Menswear",
        "index_group_no": "3",
        "index_group_name": "Menswear",
        "section_no": "27",
        "section_name": "Men Shoes",
        "garment_group_no": "1020",
        "garment_group_name": "Shoes",
        "detail_desc": "Trainers in mesh with rubber details, a padded top edge, lacing at the front and a loop front and back. Mesh linings and insoles and EVA (ethylene-vinyl acetate) and rubber soles."
    },
    {
        "article_id": "0661064002",
        "product_code": "0661064",
        "prod_name": "Victory runner",
        "product_type_no": "94",
        "product_type_name": "Sneakers",
        "product_group_name": "Shoes",
        "graphical_appearance_no": "1010016",
        "graphical_appearance_name": "Solid",
        "colour_group_code": "09",
        "colour_group_name": "Black",
        "perceived_colour_value_id": "4",
        "perceived_colour_value_name": "Dark",
        "perceived_colour_master_id": "5",
        "perceived_colour_master_name": "Black",
        "department_no": "3629",
        "department_name": "Shoes",
        "index_code": "F",
        "index_name": "Menswear",
        "index_group_no": "3",
        "index_group_name": "Menswear",
        "section_no": "27",
        "section_name": "Men Shoes",
        "garment_group_no": "1020",
        "garment_group_name": "Shoes",
        "detail_desc": "Mesh trainers with imitation leather details, a padded top edge, lacing at the front and a loop at the back. Mesh linings and insoles, and EVA (ethylene-vinyl acetate) and rubber soles."
    },
    {
        "article_id": "0661064004",
        "product_code": "0661064",
        "prod_name": "Victory runner",
        "product_type_no": "94",
        "product_type_name": "Sneakers",
        "product_group_name": "Shoes",
        "graphical_appearance_no": "1010016",
        "graphical_appearance_name": "Solid",
        "colour_group_code": "73",
        "colour_group_name": "Dark Blue",
        "perceived_colour_value_id": "2",
        "perceived_colour_value_name": "Medium Dusty",
        "perceived_colour_master_id": "2",
        "perceived_colour_master_name": "Blue",
        "department_no": "3629",
        "department_name": "Shoes",
        "index_code": "F",
        "index_name": "Menswear",
        "index_group_no": "3",
        "index_group_name": "Menswear",
        "section_no": "27",
        "section_name": "Men Shoes",
        "garment_group_no": "1020",
        "garment_group_name": "Shoes",
        "detail_desc": "Mesh trainers with imitation leather details, a padded top edge, lacing at the front and a loop at the back. Mesh linings and insoles, and EVA (ethylene-vinyl acetate) and rubber soles."
    },
    {
        "article_id": "0661067001",
        "product_code": "0661067",
        "prod_name": "SKINNY BIKER",
        "product_type_no": "272",
        "product_type_name": "Trousers",
        "product_group_name": "Garment Lower body",
        "graphical_appearance_no": "1010023",
        "graphical_appearance_name": "Denim",
        "colour_group_code": "71",
        "colour_group_name": "Light Blue",
        "perceived_colour_value_id": "1",
        "perceived_colour_value_name": "Dusty Light",
        "perceived_colour_master_id": "2",
        "perceived_colour_master_name": "Blue",
        "department_no": "7956",
        "department_name": "Kids Boy Denim",
        "index_code": "H",
        "index_name": "Children Sizes 92-140",
        "index_group_no": "4",
        "index_group_name": "Baby/Children",
        "section_no": "46",
        "section_name": "Kids Boy",
        "garment_group_no": "1016",
        "garment_group_name": "Trousers Denim",
        "detail_desc": "5-pocket slim-fit jeans in washed, stretch denim with hard-worn details, an adjustable, elasticated waist and zip fly with a press-stud. Decorative seams on the back pockets and legs with decorative stitching and narrow hems."
    },
    {
        "article_id": "0661069001",
        "product_code": "0661069",
        "prod_name": "FISH soft toy",
        "product_type_no": "78",
        "product_type_name": "Other accessories",
        "product_group_name": "Accessories",
        "graphical_appearance_no": "1010017",
        "graphical_appearance_name": "Stripe",
        "colour_group_code": "73",
        "colour_group_name": "Dark Blue",
        "perceived_colour_value_id": "5",
        "perceived_colour_value_name": "Bright",
        "perceived_colour_master_id": "2",
        "perceived_colour_master_name": "Blue",
        "department_no": "6557",
        "department_name": "Baby Exclusive",
        "index_code": "G",
        "index_name": "Baby Sizes 50-98",
        "index_group_no": "4",
        "index_group_name": "Baby/Children",
        "section_no": "44",
        "section_name": "Baby Essentials & Complements",
        "garment_group_no": "1006",
        "garment_group_name": "Woven/Jersey/Knitted mix Baby",
        "detail_desc": "Baby Exclusive. Striped soft toy in a cotton weave with embroidered details. Length approx. 17.5 cm."
    },
    {
        "article_id": "0661077001",
        "product_code": "0661077",
        "prod_name": "Relaxed Skinny PIA trash MID",
        "product_type_no": "272",
        "product_type_name": "Trousers",
        "product_group_name": "Garment Lower body",
        "graphical_appearance_no": "1010023",
        "graphical_appearance_name": "Denim",
        "colour_group_code": "71",
        "colour_group_name": "Light Blue",
        "perceived_colour_value_id": "1",
        "perceived_colour_value_name": "Dusty Light",
        "perceived_colour_master_id": "2",
        "perceived_colour_master_name": "Blue",
        "department_no": "8917",
        "department_name": "Young Girl Denim",
        "index_code": "I",
        "index_name": "Children Sizes 134-170",
        "index_group_no": "4",
        "index_group_name": "Baby/Children",
        "section_no": "77",
        "section_name": "Young Girl",
        "garment_group_no": "1016",
        "garment_group_name": "Trousers Denim",
        "detail_desc": "Slim-fit jeans in washed stretch denim with hard-worn details, an adjustable elasticated waist (in sizes 8-12Y), zip fly, fake front pockets and real back pockets."
    },
    {
        "article_id": "0661084001",
        "product_code": "0661084",
        "prod_name": "Ron high top",
        "product_type_no": "94",
        "product_type_name": "Sneakers",
        "product_group_name": "Shoes",
        "graphical_appearance_no": "1010016",
        "graphical_appearance_name": "Solid",
        "colour_group_code": "09",
        "colour_group_name": "Black",
        "perceived_colour_value_id": "4",
        "perceived_colour_value_name": "Dark",
        "perceived_colour_master_id": "5",
        "perceived_colour_master_name": "Black",
        "department_no": "3629",
        "department_name": "Shoes",
        "index_code": "F",
        "index_name": "Menswear",
        "index_group_no": "3",
        "index_group_name": "Menswear",
        "section_no": "27",
        "section_name": "Men Shoes",
        "garment_group_no": "1020",
        "garment_group_name": "Shoes",
        "detail_desc": "Hi-top trainers with a padded edge, lacing at the front and a loop at the back. Canvas insoles and rubber soles."
    },
    {
        "article_id": "0661084003",
        "product_code": "0661084",
        "prod_name": "Ron high top",
        "product_type_no": "94",
        "product_type_name": "Sneakers",
        "product_group_name": "Shoes",
        "graphical_appearance_no": "1010016",
        "graphical_appearance_name": "Solid",
        "colour_group_code": "09",
        "colour_group_name": "Black",
        "perceived_colour_value_id": "4",
        "perceived_colour_value_name": "Dark",
        "perceived_colour_master_id": "5",
        "perceived_colour_master_name": "Black",
        "department_no": "3629",
        "department_name": "Shoes",
        "index_code": "F",
        "index_name": "Menswear",
        "index_group_no": "3",
        "index_group_name": "Menswear",
        "section_no": "27",
        "section_name": "Men Shoes",
        "garment_group_no": "1020",
        "garment_group_name": "Shoes",
        "detail_desc": "Hi-top trainers with a padded edge, lacing at the front and a loop at the back. Canvas insoles and rubber soles."
    },
    {
        "article_id": "0661084007",
        "product_code": "0661084",
        "prod_name": "Ron high top",
        "product_type_no": "94",
        "product_type_name": "Sneakers",
        "product_group_name": "Shoes",
        "graphical_appearance_no": "1010016",
        "graphical_appearance_name": "Solid",
        "colour_group_code": "23",
        "colour_group_name": "Dark Yellow",
        "perceived_colour_value_id": "2",
        "perceived_colour_value_name": "Medium Dusty",
        "perceived_colour_master_id": "13",
        "perceived_colour_master_name": "Brown",
        "department_no": "3629",
        "department_name": "Shoes",
        "index_code": "F",
        "index_name": "Menswear",
        "index_group_no": "3",
        "index_group_name": "Menswear",
        "section_no": "27",
        "section_name": "Men Shoes",
        "garment_group_no": "1020",
        "garment_group_name": "Shoes",
        "detail_desc": "Hi-top trainers with a padded edge, lacing at the front and a loop at the back. Canvas insoles and rubber soles."
    },
    {
        "article_id": "0661086001",
        "product_code": "0661086",
        "prod_name": "Rodney sneaker boot PQ",
        "product_type_no": "94",
        "product_type_name": "Sneakers",
        "product_group_name": "Shoes",
        "graphical_appearance_no": "1010016",
        "graphical_appearance_name": "Solid",
        "colour_group_code": "13",
        "colour_group_name": "Beige",
        "perceived_colour_value_id": "2",
        "perceived_colour_value_name": "Medium Dusty",
        "perceived_colour_master_id": "11",
        "perceived_colour_master_name": "Beige",
        "department_no": "3629",
        "department_name": "Shoes",
        "index_code": "F",
        "index_name": "Menswear",
        "index_group_no": "3",
        "index_group_name": "Menswear",
        "section_no": "27",
        "section_name": "Men Shoes",
        "garment_group_no": "1020",
        "garment_group_name": "Shoes",
        "detail_desc": "Suede hi-tops with zips in the sides and lacing at the front. Leather linings and insoles and thermoplastic rubber (TPR) soles."
    },
    {
        "article_id": "0661090001",
        "product_code": "0661090",
        "prod_name": "Ramon high top",
        "product_type_no": "94",
        "product_type_name": "Sneakers",
        "product_group_name": "Shoes",
        "graphical_appearance_no": "1010016",
        "graphical_appearance_name": "Solid",
        "colour_group_code": "09",
        "colour_group_name": "Black",
        "perceived_colour_value_id": "4",
        "perceived_colour_value_name": "Dark",
        "perceived_colour_master_id": "5",
        "perceived_colour_master_name": "Black",
        "department_no": "3629",
        "department_name": "Shoes",
        "index_code": "F",
        "index_name": "Menswear",
        "index_group_no": "3",
        "index_group_name": "Menswear",
        "section_no": "27",
        "section_name": "Men Shoes",
        "garment_group_no": "1020",
        "garment_group_name": "Shoes",
        "detail_desc": "Fully-fashioned hi-tops with rubber details and a ribbed top edge. Mesh insoles and rubber soles."
    },
    {
        "article_id": "0661095001",
        "product_code": "0661095",
        "prod_name": "Gordon Coat PI",
        "product_type_no": "263",
        "product_type_name": "Coat",
        "product_group_name": "Garment Upper body",
        "graphical_appearance_no": "1010010",
        "graphical_appearance_name": "Melange",
        "colour_group_code": "12",
        "colour_group_name": "Light Beige",
        "perceived_colour_value_id": "1",
        "perceived_colour_value_name": "Dusty Light",
        "perceived_colour_master_id": "11",
        "perceived_colour_master_name": "Beige",
        "department_no": "1201",
        "department_name": "Outwear",
        "index_code": "A",
        "index_name": "Ladieswear",
        "index_group_no": "1",
        "index_group_name": "Ladieswear",
        "section_no": "19",
        "section_name": "Womens Jackets",
        "garment_group_no": "1007",
        "garment_group_name": "Outdoor",
        "detail_desc": "Coat in a felted wool blend with notch lapels and buttons down the front. Welt front pockets with a flap, a fake welt chest pocket, decorative buttons at the cuffs, and a single back vent. Lined."
    },
    {
        "article_id": "0661108001",
        "product_code": "0661108",
        "prod_name": "John mid court sneaker",
        "product_type_no": "94",
        "product_type_name": "Sneakers",
        "product_group_name": "Shoes",
        "graphical_appearance_no": "1010016",
        "graphical_appearance_name": "Solid",
        "colour_group_code": "09",
        "colour_group_name": "Black",
        "perceived_colour_value_id": "4",
        "perceived_colour_value_name": "Dark",
        "perceived_colour_master_id": "5",
        "perceived_colour_master_name": "Black",
        "department_no": "3629",
        "department_name": "Shoes",
        "index_code": "F",
        "index_name": "Menswear",
        "index_group_no": "3",
        "index_group_name": "Menswear",
        "section_no": "27",
        "section_name": "Men Shoes",
        "garment_group_no": "1020",
        "garment_group_name": "Shoes",
        "detail_desc": "Imitation suede trainers with a padded top edge, lacing at the front and a discreet loop at the back. Mesh linings and insoles and rubber soles."
    },
    {
        "article_id": "0661108002",
        "product_code": "0661108",
        "prod_name": "John mid court sneaker",
        "product_type_no": "94",
        "product_type_name": "Sneakers",
        "product_group_name": "Shoes",
        "graphical_appearance_no": "1010016",
        "graphical_appearance_name": "Solid",
        "colour_group_code": "73",
        "colour_group_name": "Dark Blue",
        "perceived_colour_value_id": "4",
        "perceived_colour_value_name": "Dark",
        "perceived_colour_master_id": "2",
        "perceived_colour_master_name": "Blue",
        "department_no": "3629",
        "department_name": "Shoes",
        "index_code": "F",
        "index_name": "Menswear",
        "index_group_no": "3",
        "index_group_name": "Menswear",
        "section_no": "27",
        "section_name": "Men Shoes",
        "garment_group_no": "1020",
        "garment_group_name": "Shoes",
        "detail_desc": "Imitation suede trainers with a padded top edge, lacing at the front and a discreet loop at the back. Mesh linings and insoles and rubber soles."
    },
    {
        "article_id": "0661118001",
        "product_code": "0661118",
        "prod_name": "Linni Tee",
        "product_type_no": "255",
        "product_type_name": "T-shirt",
        "product_group_name": "Garment Upper body",
        "graphical_appearance_no": "1010016",
        "graphical_appearance_name": "Solid",
        "colour_group_code": "09",
        "colour_group_name": "Black",
        "perceived_colour_value_id": "4",
        "perceived_colour_value_name": "Dark",
        "perceived_colour_master_id": "5",
        "perceived_colour_master_name": "Black",
        "department_no": "1643",
        "department_name": "Basic 1",
        "index_code": "D",
        "index_name": "Divided",
        "index_group_no": "2",
        "index_group_name": "Divided",
        "section_no": "51",
        "section_name": "Divided Basics",
        "garment_group_no": "1002",
        "garment_group_name": "Jersey Basic",
        "detail_desc": "T-shirt in soft jersey made from a cotton blend with sewn-in turn-ups on the sleeves."
    },
    {
        "article_id": "0661118002",
        "product_code": "0661118",
        "prod_name": "Linni Tee",
        "product_type_no": "255",
        "product_type_name": "T-shirt",
        "product_group_name": "Garment Upper body",
        "graphical_appearance_no": "1010016",
        "graphical_appearance_name": "Solid",
        "colour_group_code": "19",
        "colour_group_name": "Greenish Khaki",
        "perceived_colour_value_id": "2",
        "perceived_colour_value_name": "Medium Dusty",
        "perceived_colour_master_id": "20",
        "perceived_colour_master_name": "Khaki green",
        "department_no": "1643",
        "department_name": "Basic 1",
        "index_code": "D",
        "index_name": "Divided",
        "index_group_no": "2",
        "index_group_name": "Divided",
        "section_no": "51",
        "section_name": "Divided Basics",
        "garment_group_no": "1002",
        "garment_group_name": "Jersey Basic",
        "detail_desc": "T-shirt in soft jersey made from a cotton blend with sewn-in turn-ups on the sleeves."
    },
    {
        "article_id": "0661118003",
        "product_code": "0661118",
        "prod_name": "Linni Tee",
        "product_type_no": "255",
        "product_type_name": "T-shirt",
        "product_group_name": "Garment Upper body",
        "graphical_appearance_no": "1010016",
        "graphical_appearance_name": "Solid",
        "colour_group_code": "52",
        "colour_group_name": "Pink",
        "perceived_colour_value_id": "2",
        "perceived_colour_value_name": "Medium Dusty",
        "perceived_colour_master_id": "4",
        "perceived_colour_master_name": "Pink",
        "department_no": "1643",
        "department_name": "Basic 1",
        "index_code": "D",
        "index_name": "Divided",
        "index_group_no": "2",
        "index_group_name": "Divided",
        "section_no": "51",
        "section_name": "Divided Basics",
        "garment_group_no": "1002",
        "garment_group_name": "Jersey Basic",
        "detail_desc": "T-shirt in soft jersey made from a cotton blend with sewn-in turn-ups on the sleeves."
    },
    {
        "article_id": "0661120001",
        "product_code": "0661120",
        "prod_name": "SNOOD KNIT MALTE. LATE",
        "product_type_no": "80",
        "product_type_name": "Scarf",
        "product_group_name": "Accessories",
        "graphical_appearance_no": "1010026",
        "graphical_appearance_name": "Other structure",
        "colour_group_code": "73",
        "colour_group_name": "Dark Blue",
        "perceived_colour_value_id": "4",
        "perceived_colour_value_name": "Dark",
        "perceived_colour_master_id": "2",
        "perceived_colour_master_name": "Blue",
        "department_no": "4212",
        "department_name": "Kids Boy Big Acc",
        "index_code": "J",
        "index_name": "Children Accessories, Swimwear",
        "index_group_no": "4",
        "index_group_name": "Baby/Children",
        "section_no": "45",
        "section_name": "Kids Outerwear",
        "garment_group_no": "1019",
        "garment_group_name": "Accessories",
        "detail_desc": "Twisted tube scarf in a soft knit."
    },
    {
        "article_id": "0661120002",
        "product_code": "0661120",
        "prod_name": "SNOOD KNIT MALTE. LATE",
        "product_type_no": "80",
        "product_type_name": "Scarf",
        "product_group_name": "Accessories",
        "graphical_appearance_no": "1010022",
        "graphical_appearance_name": "Jacquard",
        "colour_group_code": "08",
        "colour_group_name": "Dark Grey",
        "perceived_colour_value_id": "2",
        "perceived_colour_value_name": "Medium Dusty",
        "perceived_colour_master_id": "12",
        "perceived_colour_master_name": "Grey",
        "department_no": "4212",
        "department_name": "Kids Boy Big Acc",
        "index_code": "J",
        "index_name": "Children Accessories, Swimwear",
        "index_group_no": "4",
        "index_group_name": "Baby/Children",
        "section_no": "45",
        "section_name": "Kids Outerwear",
        "garment_group_no": "1019",
        "garment_group_name": "Accessories",
        "detail_desc": "Twisted tube scarf in a soft knit."
    },
    {
        "article_id": "0661120003",
        "product_code": "0661120",
        "prod_name": "SNOOD KNIT MALTE. LATE",
        "product_type_no": "80",
        "product_type_name": "Scarf",
        "product_group_name": "Accessories",
        "graphical_appearance_no": "1010001",
        "graphical_appearance_name": "All over pattern",
        "colour_group_code": "73",
        "colour_group_name": "Dark Blue",
        "perceived_colour_value_id": "5",
        "perceived_colour_value_name": "Bright",
        "perceived_colour_master_id": "2",
        "perceived_colour_master_name": "Blue",
        "department_no": "4212",
        "department_name": "Kids Boy Big Acc",
        "index_code": "J",
        "index_name": "Children Accessories, Swimwear",
        "index_group_no": "4",
        "index_group_name": "Baby/Children",
        "section_no": "45",
        "section_name": "Kids Outerwear",
        "garment_group_no": "1019",
        "garment_group_name": "Accessories",
        "detail_desc": "Twisted tube scarf in a soft knit."
    },
    {
        "article_id": "0661120004",
        "product_code": "0661120",
        "prod_name": "SNOOD KNIT MALTE. LATE",
        "product_type_no": "80",
        "product_type_name": "Scarf",
        "product_group_name": "Accessories",
        "graphical_appearance_no": "1010017",
        "graphical_appearance_name": "Stripe",
        "colour_group_code": "33",
        "colour_group_name": "Dark Orange",
        "perceived_colour_value_id": "5",
        "perceived_colour_value_name": "Bright",
        "perceived_colour_master_id": "3",
        "perceived_colour_master_name": "Orange",
        "department_no": "4212",
        "department_name": "Kids Boy Big Acc",
        "index_code": "J",
        "index_name": "Children Accessories, Swimwear",
        "index_group_no": "4",
        "index_group_name": "Baby/Children",
        "section_no": "45",
        "section_name": "Kids Outerwear",
        "garment_group_no": "1019",
        "garment_group_name": "Accessories",
        "detail_desc": "Twisted tube scarf in a soft knit."
    },
    {
        "article_id": "0661120005",
        "product_code": "0661120",
        "prod_name": "SNOOD KNIT MALTE. LATE",
        "product_type_no": "80",
        "product_type_name": "Scarf",
        "product_group_name": "Accessories",
        "graphical_appearance_no": "1010005",
        "graphical_appearance_name": "Colour blocking",
        "colour_group_code": "09",
        "colour_group_name": "Black",
        "perceived_colour_value_id": "4",
        "perceived_colour_value_name": "Dark",
        "perceived_colour_master_id": "5",
        "perceived_colour_master_name": "Black",
        "department_no": "4212",
        "department_name": "Kids Boy Big Acc",
        "index_code": "J",
        "index_name": "Children Accessories, Swimwear",
        "index_group_no": "4",
        "index_group_name": "Baby/Children",
        "section_no": "45",
        "section_name": "Kids Outerwear",
        "garment_group_no": "1019",
        "garment_group_name": "Accessories",
        "detail_desc": "Twisted tube scarf in a soft knit."
    }
]